{
  "items": [
    {
      "track": {
        "album": {
          "album_type": "single",
          "artists": [
            {
              "external_urls": {
                "spotify": "https://open.spotify.com/artist/4tm8CEdm4pkQsEh4jIr9Yp"
              },
              "href": "https://api.spotify.com/v1/artists/4tm8CEdm4pkQsEh4jIr9Yp",
              "id": "4tm8CEdm4pkQsEh4jIr9Yp",
              "name": "Santa Fe Klan",
              "type": "artist",
              "uri": "spotify:artist:4tm8CEdm4pkQsEh4jIr9Yp"
            }
          ],
          "available_markets": [
            "AD",
            "AE",
            "AG",
            "AL",
            "AM",
            "AO",
            "AR",
            "AT",
            "AU",
            "AZ",
            "BA",
            "BB",
            "BD",
            "BE",
            "BF",
            "BG",
            "BH",
            "BI",
            "BJ",
            "BN",
            "BO",
            "BR",
            "BS",
            "BT",
            "BW",
            "BY",
            "BZ",
            "CA",
            "CD",
            "CG",
            "CH",
            "CI",
            "CL",
            "CM",
            "CO",
            "CR",
            "CV",
            "CW",
            "CY",
            "CZ",
            "DE",
            "DJ",
            "DK",
            "DM",
            "DO",
            "DZ",
            "EC",
            "EE",
            "EG",
            "ES",
            "ET",
            "FI",
            "FJ",
            "FM",
            "FR",
            "GA",
            "GB",
            "GD",
            "GE",
            "GH",
            "GM",
            "GN",
            "GQ",
            "GR",
            "GT",
            "GW",
            "GY",
            "HK",
            "HN",
            "HR",
            "HT",
            "HU",
            "ID",
            "IE",
            "IL",
            "IN",
            "IQ",
            "IS",
            "IT",
            "JM",
            "JO",
            "JP",
            "KE",
            "KG",
            "KH",
            "KI",
            "KM",
            "KN",
            "KR",
            "KW",
            "KZ",
            "LA",
            "LB",
            "LC",
            "LI",
            "LK",
            "LR",
            "LS",
            "LT",
            "LU",
            "LV",
            "LY",
            "MA",
            "MC",
            "MD",
            "ME",
            "MG",
            "MH",
            "MK",
            "ML",
            "MN",
            "MO",
            "MR",
            "MT",
            "MU",
            "MV",
            "MW",
            "MX",
            "MY",
            "MZ",
            "NA",
            "NE",
            "NG",
            "NI",
            "NL",
            "NO",
            "NP",
            "NR",
            "NZ",
            "OM",
            "PA",
            "PE",
            "PG",
            "PH",
            "PK",
            "PL",
            "PS",
            "PT",
            "PW",
            "PY",
            "QA",
            "RO",
            "RS",
            "RW",
            "SA",
            "SB",
            "SC",
            "SE",
            "SG",
            "SI",
            "SK",
            "SL",
            "SM",
            "SN",
            "SR",
            "ST",
            "SV",
            "SZ",
            "TD",
            "TG",
            "TH",
            "TJ",
            "TL",
            "TN",
            "TO",
            "TR",
            "TT",
            "TV",
            "TW",
            "TZ",
            "UA",
            "UG",
            "US",
            "UY",
            "UZ",
            "VC",
            "VE",
            "VN",
            "VU",
            "WS",
            "XK",
            "ZA",
            "ZM",
            "ZW"
          ],
          "external_urls": {
            "spotify": "https://open.spotify.com/album/60HUuuZMNdeWtayq06B0NG"
          },
          "href": "https://api.spotify.com/v1/albums/60HUuuZMNdeWtayq06B0NG",
          "id": "60HUuuZMNdeWtayq06B0NG",
          "images": [
            {
              "height": 640,
              "url": "https://i.scdn.co/image/ab67616d0000b2738f3cbbe918bd1511707791ee",
              "width": 640
            },
            {
              "height": 300,
              "url": "https://i.scdn.co/image/ab67616d00001e028f3cbbe918bd1511707791ee",
              "width": 300
            },
            {
              "height": 64,
              "url": "https://i.scdn.co/image/ab67616d000048518f3cbbe918bd1511707791ee",
              "width": 64
            }
          ],
          "name": "Silencio En El Callejon",
          "release_date": "2018-06-22",
          "release_date_precision": "day",
          "total_tracks": 1,
          "type": "album",
          "uri": "spotify:album:60HUuuZMNdeWtayq06B0NG"
        },
        "artists": [
          {
            "external_urls": {
              "spotify": "https://open.spotify.com/artist/4tm8CEdm4pkQsEh4jIr9Yp"
            },
            "href": "https://api.spotify.com/v1/artists/4tm8CEdm4pkQsEh4jIr9Yp",
            "id": "4tm8CEdm4pkQsEh4jIr9Yp",
            "name": "Santa Fe Klan",
            "type": "artist",
            "uri": "spotify:artist:4tm8CEdm4pkQsEh4jIr9Yp"
          }
        ],
        "available_markets": [
          "AR",
          "AU",
          "AT",
          "BE",
          "BO",
          "BR",
          "BG",
          "CA",
          "CL",
          "CO",
          "CR",
          "CY",
          "CZ",
          "DK",
          "DO",
          "DE",
          "EC",
          "EE",
          "SV",
          "FI",
          "FR",
          "GR",
          "GT",
          "HN",
          "HK",
          "HU",
          "IS",
          "IE",
          "IT",
          "LV",
          "LT",
          "LU",
          "MY",
          "MT",
          "MX",
          "NL",
          "NZ",
          "NI",
          "NO",
          "PA",
          "PY",
          "PE",
          "PH",
          "PL",
          "PT",
          "SG",
          "SK",
          "ES",
          "SE",
          "CH",
          "TW",
          "TR",
          "UY",
          "US",
          "GB",
          "AD",
          "LI",
          "MC",
          "ID",
          "JP",
          "TH",
          "VN",
          "RO",
          "IL",
          "ZA",
          "SA",
          "AE",
          "BH",
          "QA",
          "OM",
          "KW",
          "EG",
          "MA",
          "DZ",
          "TN",
          "LB",
          "JO",
          "PS",
          "IN",
          "BY",
          "KZ",
          "MD",
          "UA",
          "AL",
          "BA",
          "HR",
          "ME",
          "MK",
          "RS",
          "SI",
          "KR",
          "BD",
          "PK",
          "LK",
          "GH",
          "KE",
          "NG",
          "TZ",
          "UG",
          "AG",
          "AM",
          "BS",
          "BB",
          "BZ",
          "BT",
          "BW",
          "BF",
          "CV",
          "CW",
          "DM",
          "FJ",
          "GM",
          "GE",
          "GD",
          "GW",
          "GY",
          "HT",
          "JM",
          "KI",
          "LS",
          "LR",
          "MW",
          "MV",
          "ML",
          "MH",
          "FM",
          "NA",
          "NR",
          "NE",
          "PW",
          "PG",
          "WS",
          "SM",
          "ST",
          "SN",
          "SC",
          "SL",
          "SB",
          "KN",
          "LC",
          "VC",
          "SR",
          "TL",
          "TO",
          "TT",
          "TV",
          "VU",
          "AZ",
          "BN",
          "BI",
          "KH",
          "CM",
          "TD",
          "KM",
          "GQ",
          "SZ",
          "GA",
          "GN",
          "KG",
          "LA",
          "MO",
          "MR",
          "MN",
          "NP",
          "RW",
          "TG",
          "UZ",
          "ZW",
          "BJ",
          "MG",
          "MU",
          "MZ",
          "AO",
          "CI",
          "DJ",
          "ZM",
          "CD",
          "CG",
          "IQ",
          "LY",
          "TJ",
          "VE",
          "ET",
          "XK"
        ],
        "disc_number": 1,
        "duration_ms": 180062,
        "explicit": true,
        "external_ids": {
          "isrc": "USHM21849690"
        },
        "external_urls": {
          "spotify": "https://open.spotify.com/track/4erYu7HwocPKfx8EqcPY9f"
        },
        "href": "https://api.spotify.com/v1/tracks/4erYu7HwocPKfx8EqcPY9f",
        "id": "4erYu7HwocPKfx8EqcPY9f",
        "is_local": false,
        "name": "Silencio En El Callejon",
        "popularity": 61,
        "preview_url": "https://p.scdn.co/mp3-preview/7c153a0ef17ec8b209930c5f6d9629262587f3e6?cid=5a0ffed4bc0642d794ffd4ab473c1b8f",
        "track_number": 1,
        "type": "track",
        "uri": "spotify:track:4erYu7HwocPKfx8EqcPY9f"
      },
      "played_at": "2023-06-18T00:24:16.995Z",
      "context": null
    },
    {
      "track": {
        "album": {
          "album_type": "album",
          "artists": [
            {
              "external_urls": {
                "spotify": "https://open.spotify.com/artist/5MRMYpdAWZawm3ivBeWvdK"
              },
              "href": "https://api.spotify.com/v1/artists/5MRMYpdAWZawm3ivBeWvdK",
              "id": "5MRMYpdAWZawm3ivBeWvdK",
              "name": "Teeam Revolver",
              "type": "artist",
              "uri": "spotify:artist:5MRMYpdAWZawm3ivBeWvdK"
            },
            {
              "external_urls": {
                "spotify": "https://open.spotify.com/artist/4V2V4PaSblStayYVWTGDbZ"
              },
              "href": "https://api.spotify.com/v1/artists/4V2V4PaSblStayYVWTGDbZ",
              "id": "4V2V4PaSblStayYVWTGDbZ",
              "name": "Geassassin",
              "type": "artist",
              "uri": "spotify:artist:4V2V4PaSblStayYVWTGDbZ"
            }
          ],
          "available_markets": [
            "AD",
            "AE",
            "AG",
            "AL",
            "AM",
            "AO",
            "AR",
            "AT",
            "AU",
            "AZ",
            "BA",
            "BB",
            "BD",
            "BE",
            "BF",
            "BG",
            "BH",
            "BI",
            "BJ",
            "BN",
            "BO",
            "BR",
            "BS",
            "BT",
            "BW",
            "BY",
            "BZ",
            "CA",
            "CD",
            "CG",
            "CH",
            "CI",
            "CL",
            "CM",
            "CO",
            "CR",
            "CV",
            "CW",
            "CY",
            "CZ",
            "DE",
            "DJ",
            "DK",
            "DM",
            "DO",
            "DZ",
            "EC",
            "EE",
            "EG",
            "ES",
            "ET",
            "FI",
            "FJ",
            "FM",
            "FR",
            "GA",
            "GB",
            "GD",
            "GE",
            "GH",
            "GM",
            "GN",
            "GQ",
            "GR",
            "GT",
            "GW",
            "GY",
            "HK",
            "HN",
            "HR",
            "HT",
            "HU",
            "ID",
            "IE",
            "IL",
            "IN",
            "IQ",
            "IS",
            "IT",
            "JM",
            "JO",
            "JP",
            "KE",
            "KG",
            "KH",
            "KI",
            "KM",
            "KN",
            "KR",
            "KW",
            "KZ",
            "LA",
            "LB",
            "LC",
            "LI",
            "LK",
            "LR",
            "LS",
            "LT",
            "LU",
            "LV",
            "LY",
            "MA",
            "MC",
            "MD",
            "ME",
            "MG",
            "MH",
            "MK",
            "ML",
            "MN",
            "MO",
            "MR",
            "MT",
            "MU",
            "MV",
            "MW",
            "MX",
            "MY",
            "MZ",
            "NA",
            "NE",
            "NG",
            "NI",
            "NL",
            "NO",
            "NP",
            "NR",
            "NZ",
            "OM",
            "PA",
            "PE",
            "PG",
            "PH",
            "PK",
            "PL",
            "PS",
            "PT",
            "PW",
            "PY",
            "QA",
            "RO",
            "RS",
            "RW",
            "SA",
            "SB",
            "SC",
            "SE",
            "SG",
            "SI",
            "SK",
            "SL",
            "SM",
            "SN",
            "SR",
            "ST",
            "SV",
            "SZ",
            "TD",
            "TG",
            "TH",
            "TJ",
            "TL",
            "TN",
            "TO",
            "TR",
            "TT",
            "TV",
            "TW",
            "TZ",
            "UA",
            "UG",
            "US",
            "UY",
            "UZ",
            "VC",
            "VE",
            "VN",
            "VU",
            "WS",
            "XK",
            "ZA",
            "ZM",
            "ZW"
          ],
          "external_urls": {
            "spotify": "https://open.spotify.com/album/1GxhmPcuyNST8j5JEataUT"
          },
          "href": "https://api.spotify.com/v1/albums/1GxhmPcuyNST8j5JEataUT",
          "id": "1GxhmPcuyNST8j5JEataUT",
          "images": [
            {
              "height": 640,
              "url": "https://i.scdn.co/image/ab67616d0000b2732cbfbd1bc7ad4e18d2e18eb3",
              "width": 640
            },
            {
              "height": 300,
              "url": "https://i.scdn.co/image/ab67616d00001e022cbfbd1bc7ad4e18d2e18eb3",
              "width": 300
            },
            {
              "height": 64,
              "url": "https://i.scdn.co/image/ab67616d000048512cbfbd1bc7ad4e18d2e18eb3",
              "width": 64
            }
          ],
          "name": "Punto de Quiebre",
          "release_date": "2021-10-07",
          "release_date_precision": "day",
          "total_tracks": 9,
          "type": "album",
          "uri": "spotify:album:1GxhmPcuyNST8j5JEataUT"
        },
        "artists": [
          {
            "external_urls": {
              "spotify": "https://open.spotify.com/artist/5MRMYpdAWZawm3ivBeWvdK"
            },
            "href": "https://api.spotify.com/v1/artists/5MRMYpdAWZawm3ivBeWvdK",
            "id": "5MRMYpdAWZawm3ivBeWvdK",
            "name": "Teeam Revolver",
            "type": "artist",
            "uri": "spotify:artist:5MRMYpdAWZawm3ivBeWvdK"
          },
          {
            "external_urls": {
              "spotify": "https://open.spotify.com/artist/4V2V4PaSblStayYVWTGDbZ"
            },
            "href": "https://api.spotify.com/v1/artists/4V2V4PaSblStayYVWTGDbZ",
            "id": "4V2V4PaSblStayYVWTGDbZ",
            "name": "Geassassin",
            "type": "artist",
            "uri": "spotify:artist:4V2V4PaSblStayYVWTGDbZ"
          },
          {
            "external_urls": {
              "spotify": "https://open.spotify.com/artist/2hejA1Dkf8v8R0koF44FvW"
            },
            "href": "https://api.spotify.com/v1/artists/2hejA1Dkf8v8R0koF44FvW",
            "id": "2hejA1Dkf8v8R0koF44FvW",
            "name": "Gera MX",
            "type": "artist",
            "uri": "spotify:artist:2hejA1Dkf8v8R0koF44FvW"
          }
        ],
        "available_markets": [
          "AR",
          "AU",
          "AT",
          "BE",
          "BO",
          "BR",
          "BG",
          "CA",
          "CL",
          "CO",
          "CR",
          "CY",
          "CZ",
          "DK",
          "DO",
          "DE",
          "EC",
          "EE",
          "SV",
          "FI",
          "FR",
          "GR",
          "GT",
          "HN",
          "HK",
          "HU",
          "IS",
          "IE",
          "IT",
          "LV",
          "LT",
          "LU",
          "MY",
          "MT",
          "MX",
          "NL",
          "NZ",
          "NI",
          "NO",
          "PA",
          "PY",
          "PE",
          "PH",
          "PL",
          "PT",
          "SG",
          "SK",
          "ES",
          "SE",
          "CH",
          "TW",
          "TR",
          "UY",
          "US",
          "GB",
          "AD",
          "LI",
          "MC",
          "ID",
          "JP",
          "TH",
          "VN",
          "RO",
          "IL",
          "ZA",
          "SA",
          "AE",
          "BH",
          "QA",
          "OM",
          "KW",
          "EG",
          "MA",
          "DZ",
          "TN",
          "LB",
          "JO",
          "PS",
          "IN",
          "BY",
          "KZ",
          "MD",
          "UA",
          "AL",
          "BA",
          "HR",
          "ME",
          "MK",
          "RS",
          "SI",
          "KR",
          "BD",
          "PK",
          "LK",
          "GH",
          "KE",
          "NG",
          "TZ",
          "UG",
          "AG",
          "AM",
          "BS",
          "BB",
          "BZ",
          "BT",
          "BW",
          "BF",
          "CV",
          "CW",
          "DM",
          "FJ",
          "GM",
          "GE",
          "GD",
          "GW",
          "GY",
          "HT",
          "JM",
          "KI",
          "LS",
          "LR",
          "MW",
          "MV",
          "ML",
          "MH",
          "FM",
          "NA",
          "NR",
          "NE",
          "PW",
          "PG",
          "WS",
          "SM",
          "ST",
          "SN",
          "SC",
          "SL",
          "SB",
          "KN",
          "LC",
          "VC",
          "SR",
          "TL",
          "TO",
          "TT",
          "TV",
          "VU",
          "AZ",
          "BN",
          "BI",
          "KH",
          "CM",
          "TD",
          "KM",
          "GQ",
          "SZ",
          "GA",
          "GN",
          "KG",
          "LA",
          "MO",
          "MR",
          "MN",
          "NP",
          "RW",
          "TG",
          "UZ",
          "ZW",
          "BJ",
          "MG",
          "MU",
          "MZ",
          "AO",
          "CI",
          "DJ",
          "ZM",
          "CD",
          "CG",
          "IQ",
          "LY",
          "TJ",
          "VE",
          "ET",
          "XK"
        ],
        "disc_number": 1,
        "duration_ms": 263096,
        "explicit": true,
        "external_ids": {
          "isrc": "QZNJW2143631"
        },
        "external_urls": {
          "spotify": "https://open.spotify.com/track/0lBgg4RBEbDroO3SxeG5G9"
        },
        "href": "https://api.spotify.com/v1/tracks/0lBgg4RBEbDroO3SxeG5G9",
        "id": "0lBgg4RBEbDroO3SxeG5G9",
        "is_local": false,
        "name": "Sonrisa Grande, Ojos Tristes",
        "popularity": 47,
        "preview_url": "https://p.scdn.co/mp3-preview/deec5328183f4d895d454100e933d25050c8504d?cid=5a0ffed4bc0642d794ffd4ab473c1b8f",
        "track_number": 6,
        "type": "track",
        "uri": "spotify:track:0lBgg4RBEbDroO3SxeG5G9"
      },
      "played_at": "2023-06-18T00:21:17.065Z",
      "context": null
    },
    {
      "track": {
        "album": {
          "album_type": "album",
          "artists": [
            {
              "external_urls": {
                "spotify": "https://open.spotify.com/artist/6PH3FLQAxtqYy46Zv08bpV"
              },
              "href": "https://api.spotify.com/v1/artists/6PH3FLQAxtqYy46Zv08bpV",
              "id": "6PH3FLQAxtqYy46Zv08bpV",
              "name": "Ivan Cornejo",
              "type": "artist",
              "uri": "spotify:artist:6PH3FLQAxtqYy46Zv08bpV"
            }
          ],
          "available_markets": [
            "AD",
            "AE",
            "AG",
            "AL",
            "AM",
            "AO",
            "AR",
            "AT",
            "AU",
            "AZ",
            "BA",
            "BB",
            "BD",
            "BE",
            "BF",
            "BG",
            "BH",
            "BI",
            "BJ",
            "BN",
            "BO",
            "BR",
            "BS",
            "BT",
            "BW",
            "BY",
            "BZ",
            "CA",
            "CD",
            "CG",
            "CH",
            "CI",
            "CL",
            "CM",
            "CO",
            "CR",
            "CV",
            "CW",
            "CY",
            "CZ",
            "DE",
            "DJ",
            "DK",
            "DM",
            "DO",
            "DZ",
            "EC",
            "EE",
            "EG",
            "ES",
            "ET",
            "FI",
            "FJ",
            "FM",
            "FR",
            "GA",
            "GB",
            "GD",
            "GE",
            "GH",
            "GM",
            "GN",
            "GQ",
            "GR",
            "GT",
            "GW",
            "GY",
            "HK",
            "HN",
            "HR",
            "HT",
            "HU",
            "ID",
            "IE",
            "IL",
            "IN",
            "IQ",
            "IS",
            "IT",
            "JM",
            "JO",
            "JP",
            "KE",
            "KG",
            "KH",
            "KI",
            "KM",
            "KN",
            "KR",
            "KW",
            "KZ",
            "LA",
            "LB",
            "LC",
            "LI",
            "LK",
            "LR",
            "LS",
            "LT",
            "LU",
            "LV",
            "LY",
            "MA",
            "MC",
            "MD",
            "ME",
            "MG",
            "MH",
            "MK",
            "ML",
            "MN",
            "MO",
            "MR",
            "MT",
            "MU",
            "MV",
            "MW",
            "MX",
            "MY",
            "MZ",
            "NA",
            "NE",
            "NG",
            "NI",
            "NL",
            "NO",
            "NP",
            "NR",
            "NZ",
            "OM",
            "PA",
            "PE",
            "PG",
            "PH",
            "PK",
            "PL",
            "PS",
            "PT",
            "PW",
            "PY",
            "QA",
            "RO",
            "RS",
            "RW",
            "SA",
            "SB",
            "SC",
            "SE",
            "SG",
            "SI",
            "SK",
            "SL",
            "SM",
            "SN",
            "SR",
            "ST",
            "SV",
            "SZ",
            "TD",
            "TG",
            "TH",
            "TJ",
            "TL",
            "TN",
            "TO",
            "TR",
            "TT",
            "TV",
            "TW",
            "TZ",
            "UA",
            "UG",
            "US",
            "UY",
            "UZ",
            "VC",
            "VE",
            "VN",
            "VU",
            "WS",
            "XK",
            "ZA",
            "ZM",
            "ZW"
          ],
          "external_urls": {
            "spotify": "https://open.spotify.com/album/1i5VsPI1sXn847oHyXyZCh"
          },
          "href": "https://api.spotify.com/v1/albums/1i5VsPI1sXn847oHyXyZCh",
          "id": "1i5VsPI1sXn847oHyXyZCh",
          "images": [
            {
              "height": 640,
              "url": "https://i.scdn.co/image/ab67616d0000b2736d7a8a34f348d587f007045f",
              "width": 640
            },
            {
              "height": 300,
              "url": "https://i.scdn.co/image/ab67616d00001e026d7a8a34f348d587f007045f",
              "width": 300
            },
            {
              "height": 64,
              "url": "https://i.scdn.co/image/ab67616d000048516d7a8a34f348d587f007045f",
              "width": 64
            }
          ],
          "name": "Dañado",
          "release_date": "2022-06-02",
          "release_date_precision": "day",
          "total_tracks": 7,
          "type": "album",
          "uri": "spotify:album:1i5VsPI1sXn847oHyXyZCh"
        },
        "artists": [
          {
            "external_urls": {
              "spotify": "https://open.spotify.com/artist/6PH3FLQAxtqYy46Zv08bpV"
            },
            "href": "https://api.spotify.com/v1/artists/6PH3FLQAxtqYy46Zv08bpV",
            "id": "6PH3FLQAxtqYy46Zv08bpV",
            "name": "Ivan Cornejo",
            "type": "artist",
            "uri": "spotify:artist:6PH3FLQAxtqYy46Zv08bpV"
          },
          {
            "external_urls": {
              "spotify": "https://open.spotify.com/artist/0XeEobZplHxzM9QzFQWLiR"
            },
            "href": "https://api.spotify.com/v1/artists/0XeEobZplHxzM9QzFQWLiR",
            "id": "0XeEobZplHxzM9QzFQWLiR",
            "name": "Eslabon Armado",
            "type": "artist",
            "uri": "spotify:artist:0XeEobZplHxzM9QzFQWLiR"
          }
        ],
        "available_markets": [
          "AR",
          "AU",
          "AT",
          "BE",
          "BO",
          "BR",
          "BG",
          "CA",
          "CL",
          "CO",
          "CR",
          "CY",
          "CZ",
          "DK",
          "DO",
          "DE",
          "EC",
          "EE",
          "SV",
          "FI",
          "FR",
          "GR",
          "GT",
          "HN",
          "HK",
          "HU",
          "IS",
          "IE",
          "IT",
          "LV",
          "LT",
          "LU",
          "MY",
          "MT",
          "MX",
          "NL",
          "NZ",
          "NI",
          "NO",
          "PA",
          "PY",
          "PE",
          "PH",
          "PL",
          "PT",
          "SG",
          "SK",
          "ES",
          "SE",
          "CH",
          "TW",
          "TR",
          "UY",
          "US",
          "GB",
          "AD",
          "LI",
          "MC",
          "ID",
          "JP",
          "TH",
          "VN",
          "RO",
          "IL",
          "ZA",
          "SA",
          "AE",
          "BH",
          "QA",
          "OM",
          "KW",
          "EG",
          "MA",
          "DZ",
          "TN",
          "LB",
          "JO",
          "PS",
          "IN",
          "BY",
          "KZ",
          "MD",
          "UA",
          "AL",
          "BA",
          "HR",
          "ME",
          "MK",
          "RS",
          "SI",
          "KR",
          "BD",
          "PK",
          "LK",
          "GH",
          "KE",
          "NG",
          "TZ",
          "UG",
          "AG",
          "AM",
          "BS",
          "BB",
          "BZ",
          "BT",
          "BW",
          "BF",
          "CV",
          "CW",
          "DM",
          "FJ",
          "GM",
          "GE",
          "GD",
          "GW",
          "GY",
          "HT",
          "JM",
          "KI",
          "LS",
          "LR",
          "MW",
          "MV",
          "ML",
          "MH",
          "FM",
          "NA",
          "NR",
          "NE",
          "PW",
          "PG",
          "WS",
          "SM",
          "ST",
          "SN",
          "SC",
          "SL",
          "SB",
          "KN",
          "LC",
          "VC",
          "SR",
          "TL",
          "TO",
          "TT",
          "TV",
          "VU",
          "AZ",
          "BN",
          "BI",
          "KH",
          "CM",
          "TD",
          "KM",
          "GQ",
          "SZ",
          "GA",
          "GN",
          "KG",
          "LA",
          "MO",
          "MR",
          "MN",
          "NP",
          "RW",
          "TG",
          "UZ",
          "ZW",
          "BJ",
          "MG",
          "MU",
          "MZ",
          "AO",
          "CI",
          "DJ",
          "ZM",
          "CD",
          "CG",
          "IQ",
          "LY",
          "TJ",
          "VE",
          "ET",
          "XK"
        ],
        "disc_number": 1,
        "duration_ms": 216000,
        "explicit": false,
        "external_ids": {
          "isrc": "QZMFV2000317"
        },
        "external_urls": {
          "spotify": "https://open.spotify.com/track/0hnvQLkV7yOjslEzflJSK4"
        },
        "href": "https://api.spotify.com/v1/tracks/0hnvQLkV7yOjslEzflJSK4",
        "id": "0hnvQLkV7yOjslEzflJSK4",
        "is_local": false,
        "name": "La Curiosidad",
        "popularity": 80,
        "preview_url": "https://p.scdn.co/mp3-preview/f2a1a1c3d982b86620d58d4f568465daa39a8327?cid=5a0ffed4bc0642d794ffd4ab473c1b8f",
        "track_number": 5,
        "type": "track",
        "uri": "spotify:track:0hnvQLkV7yOjslEzflJSK4"
      },
      "played_at": "2023-06-18T00:15:41.114Z",
      "context": null
    },
    {
      "track": {
        "album": {
          "album_type": "album",
          "artists": [
            {
              "external_urls": {
                "spotify": "https://open.spotify.com/artist/3JSSjGYcIkgsrz7892CelT"
              },
              "href": "https://api.spotify.com/v1/artists/3JSSjGYcIkgsrz7892CelT",
              "id": "3JSSjGYcIkgsrz7892CelT",
              "name": "Ed Maverick",
              "type": "artist",
              "uri": "spotify:artist:3JSSjGYcIkgsrz7892CelT"
            }
          ],
          "available_markets": [
            "AD",
            "AE",
            "AG",
            "AL",
            "AM",
            "AO",
            "AR",
            "AT",
            "AU",
            "AZ",
            "BA",
            "BB",
            "BD",
            "BE",
            "BF",
            "BG",
            "BH",
            "BI",
            "BJ",
            "BN",
            "BO",
            "BR",
            "BS",
            "BT",
            "BW",
            "BY",
            "BZ",
            "CA",
            "CD",
            "CG",
            "CH",
            "CI",
            "CL",
            "CM",
            "CO",
            "CR",
            "CV",
            "CW",
            "CY",
            "CZ",
            "DE",
            "DJ",
            "DK",
            "DM",
            "DO",
            "DZ",
            "EC",
            "EE",
            "EG",
            "ES",
            "ET",
            "FI",
            "FJ",
            "FM",
            "FR",
            "GA",
            "GB",
            "GD",
            "GE",
            "GH",
            "GM",
            "GN",
            "GQ",
            "GR",
            "GT",
            "GW",
            "GY",
            "HK",
            "HN",
            "HR",
            "HT",
            "HU",
            "ID",
            "IE",
            "IL",
            "IN",
            "IQ",
            "IS",
            "IT",
            "JM",
            "JO",
            "JP",
            "KE",
            "KG",
            "KH",
            "KI",
            "KM",
            "KN",
            "KR",
            "KW",
            "KZ",
            "LA",
            "LB",
            "LC",
            "LI",
            "LK",
            "LR",
            "LS",
            "LT",
            "LU",
            "LV",
            "LY",
            "MA",
            "MC",
            "MD",
            "ME",
            "MG",
            "MH",
            "MK",
            "ML",
            "MN",
            "MO",
            "MR",
            "MT",
            "MU",
            "MV",
            "MW",
            "MX",
            "MY",
            "MZ",
            "NA",
            "NE",
            "NG",
            "NI",
            "NL",
            "NO",
            "NP",
            "NR",
            "NZ",
            "OM",
            "PA",
            "PE",
            "PG",
            "PH",
            "PK",
            "PL",
            "PS",
            "PT",
            "PW",
            "PY",
            "QA",
            "RO",
            "RS",
            "RW",
            "SA",
            "SB",
            "SC",
            "SE",
            "SG",
            "SI",
            "SK",
            "SL",
            "SM",
            "SN",
            "SR",
            "ST",
            "SV",
            "SZ",
            "TD",
            "TG",
            "TH",
            "TJ",
            "TL",
            "TN",
            "TO",
            "TR",
            "TT",
            "TV",
            "TW",
            "TZ",
            "UA",
            "UG",
            "US",
            "UY",
            "UZ",
            "VC",
            "VE",
            "VN",
            "VU",
            "WS",
            "XK",
            "ZA",
            "ZM",
            "ZW"
          ],
          "external_urls": {
            "spotify": "https://open.spotify.com/album/6ylPT54V3iwJY2trdxTzTX"
          },
          "href": "https://api.spotify.com/v1/albums/6ylPT54V3iwJY2trdxTzTX",
          "id": "6ylPT54V3iwJY2trdxTzTX",
          "images": [
            {
              "height": 640,
              "url": "https://i.scdn.co/image/ab67616d0000b273eab644628f8c6556d35ac9b0",
              "width": 640
            },
            {
              "height": 300,
              "url": "https://i.scdn.co/image/ab67616d00001e02eab644628f8c6556d35ac9b0",
              "width": 300
            },
            {
              "height": 64,
              "url": "https://i.scdn.co/image/ab67616d00004851eab644628f8c6556d35ac9b0",
              "width": 64
            }
          ],
          "name": "eduardo",
          "release_date": "2021-04-30",
          "release_date_precision": "day",
          "total_tracks": 12,
          "type": "album",
          "uri": "spotify:album:6ylPT54V3iwJY2trdxTzTX"
        },
        "artists": [
          {
            "external_urls": {
              "spotify": "https://open.spotify.com/artist/3JSSjGYcIkgsrz7892CelT"
            },
            "href": "https://api.spotify.com/v1/artists/3JSSjGYcIkgsrz7892CelT",
            "id": "3JSSjGYcIkgsrz7892CelT",
            "name": "Ed Maverick",
            "type": "artist",
            "uri": "spotify:artist:3JSSjGYcIkgsrz7892CelT"
          },
          {
            "external_urls": {
              "spotify": "https://open.spotify.com/artist/5ET6v0l25osw5BzztPsMvD"
            },
            "href": "https://api.spotify.com/v1/artists/5ET6v0l25osw5BzztPsMvD",
            "id": "5ET6v0l25osw5BzztPsMvD",
            "name": "Muelas De Gallo",
            "type": "artist",
            "uri": "spotify:artist:5ET6v0l25osw5BzztPsMvD"
          }
        ],
        "available_markets": [
          "AR",
          "AU",
          "AT",
          "BE",
          "BO",
          "BR",
          "BG",
          "CA",
          "CL",
          "CO",
          "CR",
          "CY",
          "CZ",
          "DK",
          "DO",
          "DE",
          "EC",
          "EE",
          "SV",
          "FI",
          "FR",
          "GR",
          "GT",
          "HN",
          "HK",
          "HU",
          "IS",
          "IE",
          "IT",
          "LV",
          "LT",
          "LU",
          "MY",
          "MT",
          "MX",
          "NL",
          "NZ",
          "NI",
          "NO",
          "PA",
          "PY",
          "PE",
          "PH",
          "PL",
          "PT",
          "SG",
          "SK",
          "ES",
          "SE",
          "CH",
          "TW",
          "TR",
          "UY",
          "US",
          "GB",
          "AD",
          "LI",
          "MC",
          "ID",
          "JP",
          "TH",
          "VN",
          "RO",
          "IL",
          "ZA",
          "SA",
          "AE",
          "BH",
          "QA",
          "OM",
          "KW",
          "EG",
          "MA",
          "DZ",
          "TN",
          "LB",
          "JO",
          "PS",
          "IN",
          "BY",
          "KZ",
          "MD",
          "UA",
          "AL",
          "BA",
          "HR",
          "ME",
          "MK",
          "RS",
          "SI",
          "KR",
          "BD",
          "PK",
          "LK",
          "GH",
          "KE",
          "NG",
          "TZ",
          "UG",
          "AG",
          "AM",
          "BS",
          "BB",
          "BZ",
          "BT",
          "BW",
          "BF",
          "CV",
          "CW",
          "DM",
          "FJ",
          "GM",
          "GE",
          "GD",
          "GW",
          "GY",
          "HT",
          "JM",
          "KI",
          "LS",
          "LR",
          "MW",
          "MV",
          "ML",
          "MH",
          "FM",
          "NA",
          "NR",
          "NE",
          "PW",
          "PG",
          "WS",
          "SM",
          "ST",
          "SN",
          "SC",
          "SL",
          "SB",
          "KN",
          "LC",
          "VC",
          "SR",
          "TL",
          "TO",
          "TT",
          "TV",
          "VU",
          "AZ",
          "BN",
          "BI",
          "KH",
          "CM",
          "TD",
          "KM",
          "GQ",
          "SZ",
          "GA",
          "GN",
          "KG",
          "LA",
          "MO",
          "MR",
          "MN",
          "NP",
          "RW",
          "TG",
          "UZ",
          "ZW",
          "BJ",
          "MG",
          "MU",
          "MZ",
          "AO",
          "CI",
          "DJ",
          "ZM",
          "CD",
          "CG",
          "IQ",
          "LY",
          "TJ",
          "VE",
          "ET",
          "XK"
        ],
        "disc_number": 1,
        "duration_ms": 267733,
        "explicit": false,
        "external_ids": {
          "isrc": "MXUM72101554"
        },
        "external_urls": {
          "spotify": "https://open.spotify.com/track/3Yle1MUxWyj8NGS4ej8vnX"
        },
        "href": "https://api.spotify.com/v1/tracks/3Yle1MUxWyj8NGS4ej8vnX",
        "id": "3Yle1MUxWyj8NGS4ej8vnX",
        "is_local": false,
        "name": "niño,",
        "popularity": 57,
        "preview_url": "https://p.scdn.co/mp3-preview/4e8c9d947522b2b0788171c25e42d78ba34dc2cd?cid=5a0ffed4bc0642d794ffd4ab473c1b8f",
        "track_number": 9,
        "type": "track",
        "uri": "spotify:track:3Yle1MUxWyj8NGS4ej8vnX"
      },
      "played_at": "2023-06-18T00:12:04.581Z",
      "context": null
    },
    {
      "track": {
        "album": {
          "album_type": "single",
          "artists": [
            {
              "external_urls": {
                "spotify": "https://open.spotify.com/artist/6tJRAxu0HwB2GI9GueEj4l"
              },
              "href": "https://api.spotify.com/v1/artists/6tJRAxu0HwB2GI9GueEj4l",
              "id": "6tJRAxu0HwB2GI9GueEj4l",
              "name": "Faruz Feet",
              "type": "artist",
              "uri": "spotify:artist:6tJRAxu0HwB2GI9GueEj4l"
            }
          ],
          "available_markets": [
            "AD",
            "AE",
            "AG",
            "AL",
            "AM",
            "AO",
            "AR",
            "AT",
            "AU",
            "AZ",
            "BA",
            "BB",
            "BD",
            "BE",
            "BF",
            "BG",
            "BH",
            "BI",
            "BJ",
            "BN",
            "BO",
            "BR",
            "BS",
            "BT",
            "BW",
            "BY",
            "BZ",
            "CA",
            "CD",
            "CG",
            "CH",
            "CI",
            "CL",
            "CM",
            "CO",
            "CR",
            "CV",
            "CW",
            "CY",
            "CZ",
            "DE",
            "DJ",
            "DK",
            "DM",
            "DO",
            "DZ",
            "EC",
            "EE",
            "EG",
            "ES",
            "ET",
            "FI",
            "FJ",
            "FM",
            "FR",
            "GA",
            "GB",
            "GD",
            "GE",
            "GH",
            "GM",
            "GN",
            "GQ",
            "GR",
            "GT",
            "GW",
            "GY",
            "HK",
            "HN",
            "HR",
            "HT",
            "HU",
            "ID",
            "IE",
            "IL",
            "IN",
            "IQ",
            "IS",
            "IT",
            "JM",
            "JO",
            "JP",
            "KE",
            "KG",
            "KH",
            "KI",
            "KM",
            "KN",
            "KR",
            "KW",
            "KZ",
            "LA",
            "LB",
            "LC",
            "LI",
            "LK",
            "LR",
            "LS",
            "LT",
            "LU",
            "LV",
            "LY",
            "MA",
            "MC",
            "MD",
            "ME",
            "MG",
            "MH",
            "MK",
            "ML",
            "MN",
            "MO",
            "MR",
            "MT",
            "MU",
            "MV",
            "MW",
            "MX",
            "MY",
            "MZ",
            "NA",
            "NE",
            "NG",
            "NI",
            "NL",
            "NO",
            "NP",
            "NR",
            "NZ",
            "OM",
            "PA",
            "PE",
            "PG",
            "PH",
            "PK",
            "PL",
            "PS",
            "PT",
            "PW",
            "PY",
            "QA",
            "RO",
            "RS",
            "RW",
            "SA",
            "SB",
            "SC",
            "SE",
            "SG",
            "SI",
            "SK",
            "SL",
            "SM",
            "SN",
            "SR",
            "ST",
            "SV",
            "SZ",
            "TD",
            "TG",
            "TH",
            "TJ",
            "TL",
            "TN",
            "TO",
            "TR",
            "TT",
            "TV",
            "TW",
            "TZ",
            "UA",
            "UG",
            "US",
            "UY",
            "UZ",
            "VC",
            "VE",
            "VN",
            "VU",
            "WS",
            "XK",
            "ZA",
            "ZM",
            "ZW"
          ],
          "external_urls": {
            "spotify": "https://open.spotify.com/album/48jy4iE2boRoHwqURX6H4Q"
          },
          "href": "https://api.spotify.com/v1/albums/48jy4iE2boRoHwqURX6H4Q",
          "id": "48jy4iE2boRoHwqURX6H4Q",
          "images": [
            {
              "height": 640,
              "url": "https://i.scdn.co/image/ab67616d0000b273b77ef5234b88511da4e5810d",
              "width": 640
            },
            {
              "height": 300,
              "url": "https://i.scdn.co/image/ab67616d00001e02b77ef5234b88511da4e5810d",
              "width": 300
            },
            {
              "height": 64,
              "url": "https://i.scdn.co/image/ab67616d00004851b77ef5234b88511da4e5810d",
              "width": 64
            }
          ],
          "name": "Mal de Amores",
          "release_date": "2021-02-26",
          "release_date_precision": "day",
          "total_tracks": 1,
          "type": "album",
          "uri": "spotify:album:48jy4iE2boRoHwqURX6H4Q"
        },
        "artists": [
          {
            "external_urls": {
              "spotify": "https://open.spotify.com/artist/6tJRAxu0HwB2GI9GueEj4l"
            },
            "href": "https://api.spotify.com/v1/artists/6tJRAxu0HwB2GI9GueEj4l",
            "id": "6tJRAxu0HwB2GI9GueEj4l",
            "name": "Faruz Feet",
            "type": "artist",
            "uri": "spotify:artist:6tJRAxu0HwB2GI9GueEj4l"
          },
          {
            "external_urls": {
              "spotify": "https://open.spotify.com/artist/0kGdWjBHBYWSJCCr5ppei3"
            },
            "href": "https://api.spotify.com/v1/artists/0kGdWjBHBYWSJCCr5ppei3",
            "id": "0kGdWjBHBYWSJCCr5ppei3",
            "name": "Key Leone",
            "type": "artist",
            "uri": "spotify:artist:0kGdWjBHBYWSJCCr5ppei3"
          }
        ],
        "available_markets": [
          "AR",
          "AU",
          "AT",
          "BE",
          "BO",
          "BR",
          "BG",
          "CA",
          "CL",
          "CO",
          "CR",
          "CY",
          "CZ",
          "DK",
          "DO",
          "DE",
          "EC",
          "EE",
          "SV",
          "FI",
          "FR",
          "GR",
          "GT",
          "HN",
          "HK",
          "HU",
          "IS",
          "IE",
          "IT",
          "LV",
          "LT",
          "LU",
          "MY",
          "MT",
          "MX",
          "NL",
          "NZ",
          "NI",
          "NO",
          "PA",
          "PY",
          "PE",
          "PH",
          "PL",
          "PT",
          "SG",
          "SK",
          "ES",
          "SE",
          "CH",
          "TW",
          "TR",
          "UY",
          "US",
          "GB",
          "AD",
          "LI",
          "MC",
          "ID",
          "JP",
          "TH",
          "VN",
          "RO",
          "IL",
          "ZA",
          "SA",
          "AE",
          "BH",
          "QA",
          "OM",
          "KW",
          "EG",
          "MA",
          "DZ",
          "TN",
          "LB",
          "JO",
          "PS",
          "IN",
          "BY",
          "KZ",
          "MD",
          "UA",
          "AL",
          "BA",
          "HR",
          "ME",
          "MK",
          "RS",
          "SI",
          "KR",
          "BD",
          "PK",
          "LK",
          "GH",
          "KE",
          "NG",
          "TZ",
          "UG",
          "AG",
          "AM",
          "BS",
          "BB",
          "BZ",
          "BT",
          "BW",
          "BF",
          "CV",
          "CW",
          "DM",
          "FJ",
          "GM",
          "GE",
          "GD",
          "GW",
          "GY",
          "HT",
          "JM",
          "KI",
          "LS",
          "LR",
          "MW",
          "MV",
          "ML",
          "MH",
          "FM",
          "NA",
          "NR",
          "NE",
          "PW",
          "PG",
          "WS",
          "SM",
          "ST",
          "SN",
          "SC",
          "SL",
          "SB",
          "KN",
          "LC",
          "VC",
          "SR",
          "TL",
          "TO",
          "TT",
          "TV",
          "VU",
          "AZ",
          "BN",
          "BI",
          "KH",
          "CM",
          "TD",
          "KM",
          "GQ",
          "SZ",
          "GA",
          "GN",
          "KG",
          "LA",
          "MO",
          "MR",
          "MN",
          "NP",
          "RW",
          "TG",
          "UZ",
          "ZW",
          "BJ",
          "MG",
          "MU",
          "MZ",
          "AO",
          "CI",
          "DJ",
          "ZM",
          "CD",
          "CG",
          "IQ",
          "LY",
          "TJ",
          "VE",
          "ET",
          "XK"
        ],
        "disc_number": 1,
        "duration_ms": 231757,
        "explicit": false,
        "external_ids": {
          "isrc": "US7VG2104491"
        },
        "external_urls": {
          "spotify": "https://open.spotify.com/track/0BIqzGHoHADris7aYGPtaw"
        },
        "href": "https://api.spotify.com/v1/tracks/0BIqzGHoHADris7aYGPtaw",
        "id": "0BIqzGHoHADris7aYGPtaw",
        "is_local": false,
        "name": "Mal de Amores",
        "popularity": 29,
        "preview_url": "https://p.scdn.co/mp3-preview/94b9a84942eb65f374f9a0f048344e025948cab5?cid=5a0ffed4bc0642d794ffd4ab473c1b8f",
        "track_number": 1,
        "type": "track",
        "uri": "spotify:track:0BIqzGHoHADris7aYGPtaw"
      },
      "played_at": "2023-06-18T00:07:36.386Z",
      "context": null
    },
    {
      "track": {
        "album": {
          "album_type": "single",
          "artists": [
            {
              "external_urls": {
                "spotify": "https://open.spotify.com/artist/12GqGscKJx3aE4t07u7eVZ"
              },
              "href": "https://api.spotify.com/v1/artists/12GqGscKJx3aE4t07u7eVZ",
              "id": "12GqGscKJx3aE4t07u7eVZ",
              "name": "Peso Pluma",
              "type": "artist",
              "uri": "spotify:artist:12GqGscKJx3aE4t07u7eVZ"
            }
          ],
          "available_markets": [
            "AD",
            "AE",
            "AG",
            "AL",
            "AM",
            "AO",
            "AR",
            "AT",
            "AU",
            "AZ",
            "BA",
            "BB",
            "BD",
            "BE",
            "BF",
            "BG",
            "BH",
            "BI",
            "BJ",
            "BN",
            "BO",
            "BR",
            "BS",
            "BT",
            "BW",
            "BY",
            "BZ",
            "CA",
            "CD",
            "CG",
            "CH",
            "CI",
            "CL",
            "CM",
            "CO",
            "CR",
            "CV",
            "CW",
            "CY",
            "CZ",
            "DE",
            "DJ",
            "DK",
            "DM",
            "DO",
            "DZ",
            "EC",
            "EE",
            "EG",
            "ES",
            "ET",
            "FI",
            "FJ",
            "FM",
            "FR",
            "GA",
            "GB",
            "GD",
            "GE",
            "GH",
            "GM",
            "GN",
            "GQ",
            "GR",
            "GT",
            "GW",
            "GY",
            "HK",
            "HN",
            "HR",
            "HT",
            "HU",
            "ID",
            "IE",
            "IL",
            "IN",
            "IQ",
            "IS",
            "IT",
            "JM",
            "JO",
            "JP",
            "KE",
            "KG",
            "KH",
            "KI",
            "KM",
            "KN",
            "KR",
            "KW",
            "KZ",
            "LA",
            "LB",
            "LC",
            "LI",
            "LK",
            "LR",
            "LS",
            "LT",
            "LU",
            "LV",
            "LY",
            "MA",
            "MC",
            "MD",
            "ME",
            "MG",
            "MH",
            "MK",
            "ML",
            "MN",
            "MO",
            "MR",
            "MT",
            "MU",
            "MV",
            "MW",
            "MX",
            "MY",
            "MZ",
            "NA",
            "NE",
            "NG",
            "NI",
            "NL",
            "NO",
            "NP",
            "NR",
            "NZ",
            "OM",
            "PA",
            "PE",
            "PG",
            "PH",
            "PK",
            "PL",
            "PS",
            "PT",
            "PW",
            "PY",
            "QA",
            "RO",
            "RS",
            "RW",
            "SA",
            "SB",
            "SC",
            "SE",
            "SG",
            "SI",
            "SK",
            "SL",
            "SM",
            "SN",
            "SR",
            "ST",
            "SV",
            "SZ",
            "TD",
            "TG",
            "TH",
            "TJ",
            "TL",
            "TN",
            "TO",
            "TR",
            "TT",
            "TV",
            "TW",
            "TZ",
            "UA",
            "UG",
            "US",
            "UY",
            "UZ",
            "VC",
            "VE",
            "VN",
            "VU",
            "WS",
            "XK",
            "ZA",
            "ZM",
            "ZW"
          ],
          "external_urls": {
            "spotify": "https://open.spotify.com/album/6USJaTtVIy0YH5hhzOWVHe"
          },
          "href": "https://api.spotify.com/v1/albums/6USJaTtVIy0YH5hhzOWVHe",
          "id": "6USJaTtVIy0YH5hhzOWVHe",
          "images": [
            {
              "height": 640,
              "url": "https://i.scdn.co/image/ab67616d0000b273427d9aa38866b43ed45f6b0c",
              "width": 640
            },
            {
              "height": 300,
              "url": "https://i.scdn.co/image/ab67616d00001e02427d9aa38866b43ed45f6b0c",
              "width": 300
            },
            {
              "height": 64,
              "url": "https://i.scdn.co/image/ab67616d00004851427d9aa38866b43ed45f6b0c",
              "width": 64
            }
          ],
          "name": "Por las Noches",
          "release_date": "2021-06-11",
          "release_date_precision": "day",
          "total_tracks": 1,
          "type": "album",
          "uri": "spotify:album:6USJaTtVIy0YH5hhzOWVHe"
        },
        "artists": [
          {
            "external_urls": {
              "spotify": "https://open.spotify.com/artist/12GqGscKJx3aE4t07u7eVZ"
            },
            "href": "https://api.spotify.com/v1/artists/12GqGscKJx3aE4t07u7eVZ",
            "id": "12GqGscKJx3aE4t07u7eVZ",
            "name": "Peso Pluma",
            "type": "artist",
            "uri": "spotify:artist:12GqGscKJx3aE4t07u7eVZ"
          }
        ],
        "available_markets": [
          "AR",
          "AU",
          "AT",
          "BE",
          "BO",
          "BR",
          "BG",
          "CA",
          "CL",
          "CO",
          "CR",
          "CY",
          "CZ",
          "DK",
          "DO",
          "DE",
          "EC",
          "EE",
          "SV",
          "FI",
          "FR",
          "GR",
          "GT",
          "HN",
          "HK",
          "HU",
          "IS",
          "IE",
          "IT",
          "LV",
          "LT",
          "LU",
          "MY",
          "MT",
          "MX",
          "NL",
          "NZ",
          "NI",
          "NO",
          "PA",
          "PY",
          "PE",
          "PH",
          "PL",
          "PT",
          "SG",
          "SK",
          "ES",
          "SE",
          "CH",
          "TW",
          "TR",
          "UY",
          "US",
          "GB",
          "AD",
          "LI",
          "MC",
          "ID",
          "JP",
          "TH",
          "VN",
          "RO",
          "IL",
          "ZA",
          "SA",
          "AE",
          "BH",
          "QA",
          "OM",
          "KW",
          "EG",
          "MA",
          "DZ",
          "TN",
          "LB",
          "JO",
          "PS",
          "IN",
          "BY",
          "KZ",
          "MD",
          "UA",
          "AL",
          "BA",
          "HR",
          "ME",
          "MK",
          "RS",
          "SI",
          "KR",
          "BD",
          "PK",
          "LK",
          "GH",
          "KE",
          "NG",
          "TZ",
          "UG",
          "AG",
          "AM",
          "BS",
          "BB",
          "BZ",
          "BT",
          "BW",
          "BF",
          "CV",
          "CW",
          "DM",
          "FJ",
          "GM",
          "GE",
          "GD",
          "GW",
          "GY",
          "HT",
          "JM",
          "KI",
          "LS",
          "LR",
          "MW",
          "MV",
          "ML",
          "MH",
          "FM",
          "NA",
          "NR",
          "NE",
          "PW",
          "PG",
          "WS",
          "SM",
          "ST",
          "SN",
          "SC",
          "SL",
          "SB",
          "KN",
          "LC",
          "VC",
          "SR",
          "TL",
          "TO",
          "TT",
          "TV",
          "VU",
          "AZ",
          "BN",
          "BI",
          "KH",
          "CM",
          "TD",
          "KM",
          "GQ",
          "SZ",
          "GA",
          "GN",
          "KG",
          "LA",
          "MO",
          "MR",
          "MN",
          "NP",
          "RW",
          "TG",
          "UZ",
          "ZW",
          "BJ",
          "MG",
          "MU",
          "MZ",
          "AO",
          "CI",
          "DJ",
          "ZM",
          "CD",
          "CG",
          "IQ",
          "LY",
          "TJ",
          "VE",
          "ET",
          "XK"
        ],
        "disc_number": 1,
        "duration_ms": 239845,
        "explicit": false,
        "external_ids": {
          "isrc": "FR96X2198154"
        },
        "external_urls": {
          "spotify": "https://open.spotify.com/track/2VzCjpKvPB1l1tqLndtAQa"
        },
        "href": "https://api.spotify.com/v1/tracks/2VzCjpKvPB1l1tqLndtAQa",
        "id": "2VzCjpKvPB1l1tqLndtAQa",
        "is_local": false,
        "name": "Por las Noches",
        "popularity": 93,
        "preview_url": "https://p.scdn.co/mp3-preview/ba2f667c373e2d12343ac00b162886caca060c93?cid=5a0ffed4bc0642d794ffd4ab473c1b8f",
        "track_number": 1,
        "type": "track",
        "uri": "spotify:track:2VzCjpKvPB1l1tqLndtAQa"
      },
      "played_at": "2023-06-18T00:03:43.533Z",
      "context": null
    },
    {
      "track": {
        "album": {
          "album_type": "single",
          "artists": [
            {
              "external_urls": {
                "spotify": "https://open.spotify.com/artist/12GqGscKJx3aE4t07u7eVZ"
              },
              "href": "https://api.spotify.com/v1/artists/12GqGscKJx3aE4t07u7eVZ",
              "id": "12GqGscKJx3aE4t07u7eVZ",
              "name": "Peso Pluma",
              "type": "artist",
              "uri": "spotify:artist:12GqGscKJx3aE4t07u7eVZ"
            }
          ],
          "available_markets": [
            "AD",
            "AE",
            "AG",
            "AL",
            "AM",
            "AO",
            "AR",
            "AT",
            "AU",
            "AZ",
            "BA",
            "BB",
            "BD",
            "BE",
            "BF",
            "BG",
            "BH",
            "BI",
            "BJ",
            "BN",
            "BO",
            "BR",
            "BS",
            "BT",
            "BW",
            "BY",
            "BZ",
            "CA",
            "CD",
            "CG",
            "CH",
            "CI",
            "CL",
            "CM",
            "CO",
            "CR",
            "CV",
            "CW",
            "CY",
            "CZ",
            "DE",
            "DJ",
            "DK",
            "DM",
            "DO",
            "DZ",
            "EC",
            "EE",
            "EG",
            "ES",
            "ET",
            "FI",
            "FJ",
            "FM",
            "FR",
            "GA",
            "GB",
            "GD",
            "GE",
            "GH",
            "GM",
            "GN",
            "GQ",
            "GR",
            "GT",
            "GW",
            "GY",
            "HK",
            "HN",
            "HR",
            "HT",
            "HU",
            "ID",
            "IE",
            "IL",
            "IN",
            "IQ",
            "IS",
            "IT",
            "JM",
            "JO",
            "JP",
            "KE",
            "KG",
            "KH",
            "KI",
            "KM",
            "KN",
            "KR",
            "KW",
            "KZ",
            "LA",
            "LB",
            "LC",
            "LI",
            "LK",
            "LR",
            "LS",
            "LT",
            "LU",
            "LV",
            "LY",
            "MA",
            "MC",
            "MD",
            "ME",
            "MG",
            "MH",
            "MK",
            "ML",
            "MN",
            "MO",
            "MR",
            "MT",
            "MU",
            "MV",
            "MW",
            "MX",
            "MY",
            "MZ",
            "NA",
            "NE",
            "NG",
            "NI",
            "NL",
            "NO",
            "NP",
            "NR",
            "NZ",
            "OM",
            "PA",
            "PE",
            "PG",
            "PH",
            "PK",
            "PL",
            "PS",
            "PT",
            "PW",
            "PY",
            "QA",
            "RO",
            "RS",
            "RW",
            "SA",
            "SB",
            "SC",
            "SE",
            "SG",
            "SI",
            "SK",
            "SL",
            "SM",
            "SN",
            "SR",
            "ST",
            "SV",
            "SZ",
            "TD",
            "TG",
            "TH",
            "TJ",
            "TL",
            "TN",
            "TO",
            "TR",
            "TT",
            "TV",
            "TW",
            "TZ",
            "UA",
            "UG",
            "US",
            "UY",
            "UZ",
            "VC",
            "VE",
            "VN",
            "VU",
            "WS",
            "XK",
            "ZA",
            "ZM",
            "ZW"
          ],
          "external_urls": {
            "spotify": "https://open.spotify.com/album/6USJaTtVIy0YH5hhzOWVHe"
          },
          "href": "https://api.spotify.com/v1/albums/6USJaTtVIy0YH5hhzOWVHe",
          "id": "6USJaTtVIy0YH5hhzOWVHe",
          "images": [
            {
              "height": 640,
              "url": "https://i.scdn.co/image/ab67616d0000b273427d9aa38866b43ed45f6b0c",
              "width": 640
            },
            {
              "height": 300,
              "url": "https://i.scdn.co/image/ab67616d00001e02427d9aa38866b43ed45f6b0c",
              "width": 300
            },
            {
              "height": 64,
              "url": "https://i.scdn.co/image/ab67616d00004851427d9aa38866b43ed45f6b0c",
              "width": 64
            }
          ],
          "name": "Por las Noches",
          "release_date": "2021-06-11",
          "release_date_precision": "day",
          "total_tracks": 1,
          "type": "album",
          "uri": "spotify:album:6USJaTtVIy0YH5hhzOWVHe"
        },
        "artists": [
          {
            "external_urls": {
              "spotify": "https://open.spotify.com/artist/12GqGscKJx3aE4t07u7eVZ"
            },
            "href": "https://api.spotify.com/v1/artists/12GqGscKJx3aE4t07u7eVZ",
            "id": "12GqGscKJx3aE4t07u7eVZ",
            "name": "Peso Pluma",
            "type": "artist",
            "uri": "spotify:artist:12GqGscKJx3aE4t07u7eVZ"
          }
        ],
        "available_markets": [
          "AR",
          "AU",
          "AT",
          "BE",
          "BO",
          "BR",
          "BG",
          "CA",
          "CL",
          "CO",
          "CR",
          "CY",
          "CZ",
          "DK",
          "DO",
          "DE",
          "EC",
          "EE",
          "SV",
          "FI",
          "FR",
          "GR",
          "GT",
          "HN",
          "HK",
          "HU",
          "IS",
          "IE",
          "IT",
          "LV",
          "LT",
          "LU",
          "MY",
          "MT",
          "MX",
          "NL",
          "NZ",
          "NI",
          "NO",
          "PA",
          "PY",
          "PE",
          "PH",
          "PL",
          "PT",
          "SG",
          "SK",
          "ES",
          "SE",
          "CH",
          "TW",
          "TR",
          "UY",
          "US",
          "GB",
          "AD",
          "LI",
          "MC",
          "ID",
          "JP",
          "TH",
          "VN",
          "RO",
          "IL",
          "ZA",
          "SA",
          "AE",
          "BH",
          "QA",
          "OM",
          "KW",
          "EG",
          "MA",
          "DZ",
          "TN",
          "LB",
          "JO",
          "PS",
          "IN",
          "BY",
          "KZ",
          "MD",
          "UA",
          "AL",
          "BA",
          "HR",
          "ME",
          "MK",
          "RS",
          "SI",
          "KR",
          "BD",
          "PK",
          "LK",
          "GH",
          "KE",
          "NG",
          "TZ",
          "UG",
          "AG",
          "AM",
          "BS",
          "BB",
          "BZ",
          "BT",
          "BW",
          "BF",
          "CV",
          "CW",
          "DM",
          "FJ",
          "GM",
          "GE",
          "GD",
          "GW",
          "GY",
          "HT",
          "JM",
          "KI",
          "LS",
          "LR",
          "MW",
          "MV",
          "ML",
          "MH",
          "FM",
          "NA",
          "NR",
          "NE",
          "PW",
          "PG",
          "WS",
          "SM",
          "ST",
          "SN",
          "SC",
          "SL",
          "SB",
          "KN",
          "LC",
          "VC",
          "SR",
          "TL",
          "TO",
          "TT",
          "TV",
          "VU",
          "AZ",
          "BN",
          "BI",
          "KH",
          "CM",
          "TD",
          "KM",
          "GQ",
          "SZ",
          "GA",
          "GN",
          "KG",
          "LA",
          "MO",
          "MR",
          "MN",
          "NP",
          "RW",
          "TG",
          "UZ",
          "ZW",
          "BJ",
          "MG",
          "MU",
          "MZ",
          "AO",
          "CI",
          "DJ",
          "ZM",
          "CD",
          "CG",
          "IQ",
          "LY",
          "TJ",
          "VE",
          "ET",
          "XK"
        ],
        "disc_number": 1,
        "duration_ms": 239845,
        "explicit": false,
        "external_ids": {
          "isrc": "FR96X2198154"
        },
        "external_urls": {
          "spotify": "https://open.spotify.com/track/2VzCjpKvPB1l1tqLndtAQa"
        },
        "href": "https://api.spotify.com/v1/tracks/2VzCjpKvPB1l1tqLndtAQa",
        "id": "2VzCjpKvPB1l1tqLndtAQa",
        "is_local": false,
        "name": "Por las Noches",
        "popularity": 93,
        "preview_url": "https://p.scdn.co/mp3-preview/ba2f667c373e2d12343ac00b162886caca060c93?cid=5a0ffed4bc0642d794ffd4ab473c1b8f",
        "track_number": 1,
        "type": "track",
        "uri": "spotify:track:2VzCjpKvPB1l1tqLndtAQa"
      },
      "played_at": "2023-06-17T14:23:40.784Z",
      "context": null
    },
    {
      "track": {
        "album": {
          "album_type": "single",
          "artists": [
            {
              "external_urls": {
                "spotify": "https://open.spotify.com/artist/6viZnVSHavFUcW0blu6Mvw"
              },
              "href": "https://api.spotify.com/v1/artists/6viZnVSHavFUcW0blu6Mvw",
              "id": "6viZnVSHavFUcW0blu6Mvw",
              "name": "Simpson Ahuevo",
              "type": "artist",
              "uri": "spotify:artist:6viZnVSHavFUcW0blu6Mvw"
            }
          ],
          "available_markets": [
            "AD",
            "AE",
            "AG",
            "AL",
            "AM",
            "AO",
            "AR",
            "AT",
            "AU",
            "AZ",
            "BA",
            "BB",
            "BD",
            "BE",
            "BF",
            "BG",
            "BH",
            "BI",
            "BJ",
            "BN",
            "BO",
            "BR",
            "BS",
            "BT",
            "BW",
            "BY",
            "BZ",
            "CA",
            "CD",
            "CG",
            "CH",
            "CI",
            "CL",
            "CM",
            "CO",
            "CR",
            "CV",
            "CW",
            "CY",
            "CZ",
            "DE",
            "DJ",
            "DK",
            "DM",
            "DO",
            "DZ",
            "EC",
            "EE",
            "EG",
            "ES",
            "ET",
            "FI",
            "FJ",
            "FM",
            "FR",
            "GA",
            "GB",
            "GD",
            "GE",
            "GH",
            "GM",
            "GN",
            "GQ",
            "GR",
            "GT",
            "GW",
            "GY",
            "HK",
            "HN",
            "HR",
            "HT",
            "HU",
            "ID",
            "IE",
            "IL",
            "IN",
            "IQ",
            "IS",
            "IT",
            "JM",
            "JO",
            "JP",
            "KE",
            "KG",
            "KH",
            "KI",
            "KM",
            "KN",
            "KR",
            "KW",
            "KZ",
            "LA",
            "LB",
            "LC",
            "LI",
            "LK",
            "LR",
            "LS",
            "LT",
            "LU",
            "LV",
            "LY",
            "MA",
            "MC",
            "MD",
            "ME",
            "MG",
            "MH",
            "MK",
            "ML",
            "MN",
            "MO",
            "MR",
            "MT",
            "MU",
            "MV",
            "MW",
            "MX",
            "MY",
            "MZ",
            "NA",
            "NE",
            "NG",
            "NI",
            "NL",
            "NO",
            "NP",
            "NR",
            "NZ",
            "OM",
            "PA",
            "PE",
            "PG",
            "PH",
            "PK",
            "PL",
            "PS",
            "PT",
            "PW",
            "PY",
            "QA",
            "RO",
            "RS",
            "RW",
            "SA",
            "SB",
            "SC",
            "SE",
            "SG",
            "SI",
            "SK",
            "SL",
            "SM",
            "SN",
            "SR",
            "ST",
            "SV",
            "SZ",
            "TD",
            "TG",
            "TH",
            "TJ",
            "TL",
            "TN",
            "TO",
            "TR",
            "TT",
            "TV",
            "TW",
            "TZ",
            "UA",
            "UG",
            "US",
            "UY",
            "UZ",
            "VC",
            "VE",
            "VN",
            "VU",
            "WS",
            "XK",
            "ZA",
            "ZM",
            "ZW"
          ],
          "external_urls": {
            "spotify": "https://open.spotify.com/album/59IkAXXPqzP6DOuYsQ696T"
          },
          "href": "https://api.spotify.com/v1/albums/59IkAXXPqzP6DOuYsQ696T",
          "id": "59IkAXXPqzP6DOuYsQ696T",
          "images": [
            {
              "height": 640,
              "url": "https://i.scdn.co/image/ab67616d0000b2730bb66111ca2f1c8ef82d27b1",
              "width": 640
            },
            {
              "height": 300,
              "url": "https://i.scdn.co/image/ab67616d00001e020bb66111ca2f1c8ef82d27b1",
              "width": 300
            },
            {
              "height": 64,
              "url": "https://i.scdn.co/image/ab67616d000048510bb66111ca2f1c8ef82d27b1",
              "width": 64
            }
          ],
          "name": "Duele",
          "release_date": "2020-11-27",
          "release_date_precision": "day",
          "total_tracks": 1,
          "type": "album",
          "uri": "spotify:album:59IkAXXPqzP6DOuYsQ696T"
        },
        "artists": [
          {
            "external_urls": {
              "spotify": "https://open.spotify.com/artist/6viZnVSHavFUcW0blu6Mvw"
            },
            "href": "https://api.spotify.com/v1/artists/6viZnVSHavFUcW0blu6Mvw",
            "id": "6viZnVSHavFUcW0blu6Mvw",
            "name": "Simpson Ahuevo",
            "type": "artist",
            "uri": "spotify:artist:6viZnVSHavFUcW0blu6Mvw"
          }
        ],
        "available_markets": [
          "AR",
          "AU",
          "AT",
          "BE",
          "BO",
          "BR",
          "BG",
          "CA",
          "CL",
          "CO",
          "CR",
          "CY",
          "CZ",
          "DK",
          "DO",
          "DE",
          "EC",
          "EE",
          "SV",
          "FI",
          "FR",
          "GR",
          "GT",
          "HN",
          "HK",
          "HU",
          "IS",
          "IE",
          "IT",
          "LV",
          "LT",
          "LU",
          "MY",
          "MT",
          "MX",
          "NL",
          "NZ",
          "NI",
          "NO",
          "PA",
          "PY",
          "PE",
          "PH",
          "PL",
          "PT",
          "SG",
          "SK",
          "ES",
          "SE",
          "CH",
          "TW",
          "TR",
          "UY",
          "US",
          "GB",
          "AD",
          "LI",
          "MC",
          "ID",
          "JP",
          "TH",
          "VN",
          "RO",
          "IL",
          "ZA",
          "SA",
          "AE",
          "BH",
          "QA",
          "OM",
          "KW",
          "EG",
          "MA",
          "DZ",
          "TN",
          "LB",
          "JO",
          "PS",
          "IN",
          "BY",
          "KZ",
          "MD",
          "UA",
          "AL",
          "BA",
          "HR",
          "ME",
          "MK",
          "RS",
          "SI",
          "KR",
          "BD",
          "PK",
          "LK",
          "GH",
          "KE",
          "NG",
          "TZ",
          "UG",
          "AG",
          "AM",
          "BS",
          "BB",
          "BZ",
          "BT",
          "BW",
          "BF",
          "CV",
          "CW",
          "DM",
          "FJ",
          "GM",
          "GE",
          "GD",
          "GW",
          "GY",
          "HT",
          "JM",
          "KI",
          "LS",
          "LR",
          "MW",
          "MV",
          "ML",
          "MH",
          "FM",
          "NA",
          "NR",
          "NE",
          "PW",
          "PG",
          "WS",
          "SM",
          "ST",
          "SN",
          "SC",
          "SL",
          "SB",
          "KN",
          "LC",
          "VC",
          "SR",
          "TL",
          "TO",
          "TT",
          "TV",
          "VU",
          "AZ",
          "BN",
          "BI",
          "KH",
          "CM",
          "TD",
          "KM",
          "GQ",
          "SZ",
          "GA",
          "GN",
          "KG",
          "LA",
          "MO",
          "MR",
          "MN",
          "NP",
          "RW",
          "TG",
          "UZ",
          "ZW",
          "BJ",
          "MG",
          "MU",
          "MZ",
          "AO",
          "CI",
          "DJ",
          "ZM",
          "CD",
          "CG",
          "IQ",
          "LY",
          "TJ",
          "VE",
          "ET",
          "XK"
        ],
        "disc_number": 1,
        "duration_ms": 159007,
        "explicit": false,
        "external_ids": {
          "isrc": "FR26V2029838"
        },
        "external_urls": {
          "spotify": "https://open.spotify.com/track/0vp1LRAhFT6PK9ixOmFT6E"
        },
        "href": "https://api.spotify.com/v1/tracks/0vp1LRAhFT6PK9ixOmFT6E",
        "id": "0vp1LRAhFT6PK9ixOmFT6E",
        "is_local": false,
        "name": "Duele",
        "popularity": 55,
        "preview_url": "https://p.scdn.co/mp3-preview/68f1bd9491349e6636a37e70e82e0d635a35334c?cid=5a0ffed4bc0642d794ffd4ab473c1b8f",
        "track_number": 1,
        "type": "track",
        "uri": "spotify:track:0vp1LRAhFT6PK9ixOmFT6E"
      },
      "played_at": "2023-06-17T14:20:38.864Z",
      "context": null
    }
  ]
}
