{
  "items": [
    {
      "track": {
        "album": {
          "album_type": "single",
          "artists": [
            {
              "external_urls": {
                "spotify": "https://open.spotify.com/artist/4AxSQnOMPd42KI149MWsub"
              },
              "href": "https://api.spotify.com/v1/artists/4AxSQnOMPd42KI149MWsub",
              "id": "4AxSQnOMPd42KI149MWsub",
              "name": "Eddie Zuko",
              "type": "artist",
              "uri": "spotify:artist:4AxSQnOMPd42KI149MWsub"
            },
            {
              "external_urls": {
                "spotify": "https://open.spotify.com/artist/6Dcufc8lKB2eVG5JKnT5fZ"
              },
              "href": "https://api.spotify.com/v1/artists/6Dcufc8lKB2eVG5JKnT5fZ",
              "id": "6Dcufc8lKB2eVG5JKnT5fZ",
              "name": "Vel Nine",
              "type": "artist",
              "uri": "spotify:artist:6Dcufc8lKB2eVG5JKnT5fZ"
            }
          ],
          "available_markets": [
            "AR",
            "AU",
            "AT",
            "BE",
            "BO",
            "BR",
            "BG",
            "CA",
            "CL",
            "CO",
            "CR",
            "CY",
            "CZ",
            "DK",
            "DO",
            "DE",
            "EC",
            "EE",
            "SV",
            "FI",
            "FR",
            "GR",
            "GT",
            "HN",
            "HK",
            "HU",
            "IS",
            "IE",
            "IT",
            "LV",
            "LT",
            "LU",
            "MY",
            "MT",
            "MX",
            "NL",
            "NZ",
            "NI",
            "NO",
            "PA",
            "PY",
            "PE",
            "PH",
            "PL",
            "PT",
            "SG",
            "SK",
            "ES",
            "SE",
            "CH",
            "TW",
            "TR",
            "UY",
            "US",
            "GB",
            "AD",
            "LI",
            "MC",
            "ID",
            "JP",
            "TH",
            "VN",
            "RO",
            "IL",
            "ZA",
            "SA",
            "AE",
            "BH",
            "QA",
            "OM",
            "KW",
            "EG",
            "MA",
            "DZ",
            "TN",
            "LB",
            "JO",
            "PS",
            "IN",
            "KZ",
            "MD",
            "UA",
            "AL",
            "BA",
            "HR",
            "ME",
            "MK",
            "RS",
            "SI",
            "KR",
            "BD",
            "PK",
            "LK",
            "GH",
            "KE",
            "NG",
            "TZ",
            "UG",
            "AG",
            "AM",
            "BS",
            "BB",
            "BZ",
            "BT",
            "BW",
            "BF",
            "CV",
            "CW",
            "DM",
            "FJ",
            "GM",
            "GE",
            "GD",
            "GW",
            "GY",
            "HT",
            "JM",
            "KI",
            "LS",
            "LR",
            "MW",
            "MV",
            "ML",
            "MH",
            "FM",
            "NA",
            "NR",
            "NE",
            "PW",
            "PG",
            "WS",
            "SM",
            "ST",
            "SN",
            "SC",
            "SL",
            "SB",
            "KN",
            "LC",
            "VC",
            "SR",
            "TL",
            "TO",
            "TT",
            "TV",
            "VU",
            "AZ",
            "BN",
            "BI",
            "KH",
            "CM",
            "TD",
            "KM",
            "GQ",
            "SZ",
            "GA",
            "GN",
            "KG",
            "LA",
            "MO",
            "MR",
            "MN",
            "NP",
            "RW",
            "TG",
            "UZ",
            "ZW",
            "BJ",
            "MG",
            "MU",
            "MZ",
            "AO",
            "CI",
            "DJ",
            "ZM",
            "CD",
            "CG",
            "IQ",
            "LY",
            "TJ",
            "VE",
            "ET",
            "XK"
          ],
          "external_urls": {
            "spotify": "https://open.spotify.com/album/6YJswsXq0FU1XunW5FsN6Q"
          },
          "href": "https://api.spotify.com/v1/albums/6YJswsXq0FU1XunW5FsN6Q",
          "id": "6YJswsXq0FU1XunW5FsN6Q",
          "images": [
            {
              "height": 640,
              "url": "https://i.scdn.co/image/ab67616d0000b273b1cc1f5c285d0eef30982734",
              "width": 640
            },
            {
              "height": 300,
              "url": "https://i.scdn.co/image/ab67616d00001e02b1cc1f5c285d0eef30982734",
              "width": 300
            },
            {
              "height": 64,
              "url": "https://i.scdn.co/image/ab67616d00004851b1cc1f5c285d0eef30982734",
              "width": 64
            }
          ],
          "name": "Out Of My Mind",
          "release_date": "2021-02-12",
          "release_date_precision": "day",
          "total_tracks": 1,
          "type": "album",
          "uri": "spotify:album:6YJswsXq0FU1XunW5FsN6Q"
        },
        "artists": [
          {
            "external_urls": {
              "spotify": "https://open.spotify.com/artist/4AxSQnOMPd42KI149MWsub"
            },
            "href": "https://api.spotify.com/v1/artists/4AxSQnOMPd42KI149MWsub",
            "id": "4AxSQnOMPd42KI149MWsub",
            "name": "Eddie Zuko",
            "type": "artist",
            "uri": "spotify:artist:4AxSQnOMPd42KI149MWsub"
          },
          {
            "external_urls": {
              "spotify": "https://open.spotify.com/artist/6Dcufc8lKB2eVG5JKnT5fZ"
            },
            "href": "https://api.spotify.com/v1/artists/6Dcufc8lKB2eVG5JKnT5fZ",
            "id": "6Dcufc8lKB2eVG5JKnT5fZ",
            "name": "Vel Nine",
            "type": "artist",
            "uri": "spotify:artist:6Dcufc8lKB2eVG5JKnT5fZ"
          }
        ],
        "available_markets": [
          "AR",
          "AU",
          "AT",
          "BE",
          "BO",
          "BR",
          "BG",
          "CA",
          "CL",
          "CO",
          "CR",
          "CY",
          "CZ",
          "DK",
          "DO",
          "DE",
          "EC",
          "EE",
          "SV",
          "FI",
          "FR",
          "GR",
          "GT",
          "HN",
          "HK",
          "HU",
          "IS",
          "IE",
          "IT",
          "LV",
          "LT",
          "LU",
          "MY",
          "MT",
          "MX",
          "NL",
          "NZ",
          "NI",
          "NO",
          "PA",
          "PY",
          "PE",
          "PH",
          "PL",
          "PT",
          "SG",
          "SK",
          "ES",
          "SE",
          "CH",
          "TW",
          "TR",
          "UY",
          "US",
          "GB",
          "AD",
          "LI",
          "MC",
          "ID",
          "JP",
          "TH",
          "VN",
          "RO",
          "IL",
          "ZA",
          "SA",
          "AE",
          "BH",
          "QA",
          "OM",
          "KW",
          "EG",
          "MA",
          "DZ",
          "TN",
          "LB",
          "JO",
          "PS",
          "IN",
          "KZ",
          "MD",
          "UA",
          "AL",
          "BA",
          "HR",
          "ME",
          "MK",
          "RS",
          "SI",
          "KR",
          "BD",
          "PK",
          "LK",
          "GH",
          "KE",
          "NG",
          "TZ",
          "UG",
          "AG",
          "AM",
          "BS",
          "BB",
          "BZ",
          "BT",
          "BW",
          "BF",
          "CV",
          "CW",
          "DM",
          "FJ",
          "GM",
          "GE",
          "GD",
          "GW",
          "GY",
          "HT",
          "JM",
          "KI",
          "LS",
          "LR",
          "MW",
          "MV",
          "ML",
          "MH",
          "FM",
          "NA",
          "NR",
          "NE",
          "PW",
          "PG",
          "WS",
          "SM",
          "ST",
          "SN",
          "SC",
          "SL",
          "SB",
          "KN",
          "LC",
          "VC",
          "SR",
          "TL",
          "TO",
          "TT",
          "TV",
          "VU",
          "AZ",
          "BN",
          "BI",
          "KH",
          "CM",
          "TD",
          "KM",
          "GQ",
          "SZ",
          "GA",
          "GN",
          "KG",
          "LA",
          "MO",
          "MR",
          "MN",
          "NP",
          "RW",
          "TG",
          "UZ",
          "ZW",
          "BJ",
          "MG",
          "MU",
          "MZ",
          "AO",
          "CI",
          "DJ",
          "ZM",
          "CD",
          "CG",
          "IQ",
          "LY",
          "TJ",
          "VE",
          "ET",
          "XK"
        ],
        "disc_number": 1,
        "duration_ms": 257680,
        "explicit": true,
        "external_ids": {
          "isrc": "USLD91730940"
        },
        "external_urls": {
          "spotify": "https://open.spotify.com/track/7p7GBCtcGCNpdoj5CBBxfs"
        },
        "href": "https://api.spotify.com/v1/tracks/7p7GBCtcGCNpdoj5CBBxfs",
        "id": "7p7GBCtcGCNpdoj5CBBxfs",
        "is_local": false,
        "name": "Out Of My Mind",
        "popularity": 35,
        "preview_url": "https://p.scdn.co/mp3-preview/be269d77ab210cd595358d49caebe17e603ba780?cid=5a0ffed4bc0642d794ffd4ab473c1b8f",
        "track_number": 1,
        "type": "track",
        "uri": "spotify:track:7p7GBCtcGCNpdoj5CBBxfs"
      },
      "played_at": "2023-10-09T22:16:13.578Z",
      "context": null
    },
    {
      "track": {
        "album": {
          "album_type": "album",
          "artists": [
            {
              "external_urls": {
                "spotify": "https://open.spotify.com/artist/4q3ewBCX7sLwd24euuV69X"
              },
              "href": "https://api.spotify.com/v1/artists/4q3ewBCX7sLwd24euuV69X",
              "id": "4q3ewBCX7sLwd24euuV69X",
              "name": "Bad Bunny",
              "type": "artist",
              "uri": "spotify:artist:4q3ewBCX7sLwd24euuV69X"
            }
          ],
          "available_markets": [
            "AR",
            "AU",
            "AT",
            "BE",
            "BO",
            "BR",
            "BG",
            "CA",
            "CL",
            "CO",
            "CR",
            "CY",
            "CZ",
            "DK",
            "DO",
            "DE",
            "EC",
            "EE",
            "SV",
            "FI",
            "FR",
            "GR",
            "GT",
            "HN",
            "HK",
            "HU",
            "IS",
            "IE",
            "IT",
            "LV",
            "LT",
            "LU",
            "MY",
            "MT",
            "MX",
            "NL",
            "NZ",
            "NI",
            "NO",
            "PA",
            "PY",
            "PE",
            "PH",
            "PL",
            "PT",
            "SG",
            "SK",
            "ES",
            "SE",
            "CH",
            "TW",
            "TR",
            "UY",
            "US",
            "GB",
            "AD",
            "LI",
            "MC",
            "ID",
            "JP",
            "TH",
            "VN",
            "RO",
            "IL",
            "ZA",
            "SA",
            "AE",
            "BH",
            "QA",
            "OM",
            "KW",
            "EG",
            "MA",
            "DZ",
            "TN",
            "LB",
            "JO",
            "PS",
            "IN",
            "BY",
            "KZ",
            "MD",
            "UA",
            "AL",
            "BA",
            "HR",
            "ME",
            "MK",
            "RS",
            "SI",
            "KR",
            "BD",
            "PK",
            "LK",
            "GH",
            "KE",
            "NG",
            "TZ",
            "UG",
            "AG",
            "AM",
            "BS",
            "BB",
            "BZ",
            "BT",
            "BW",
            "BF",
            "CV",
            "CW",
            "DM",
            "FJ",
            "GM",
            "GE",
            "GD",
            "GW",
            "GY",
            "HT",
            "JM",
            "KI",
            "LS",
            "LR",
            "MW",
            "MV",
            "ML",
            "MH",
            "FM",
            "NA",
            "NR",
            "NE",
            "PW",
            "PG",
            "WS",
            "SM",
            "ST",
            "SN",
            "SC",
            "SL",
            "SB",
            "KN",
            "LC",
            "VC",
            "SR",
            "TL",
            "TO",
            "TT",
            "TV",
            "VU",
            "AZ",
            "BN",
            "BI",
            "KH",
            "CM",
            "TD",
            "KM",
            "GQ",
            "SZ",
            "GA",
            "GN",
            "KG",
            "LA",
            "MO",
            "MR",
            "MN",
            "NP",
            "RW",
            "TG",
            "UZ",
            "ZW",
            "BJ",
            "MG",
            "MU",
            "MZ",
            "AO",
            "CI",
            "DJ",
            "ZM",
            "CD",
            "CG",
            "IQ",
            "LY",
            "TJ",
            "VE",
            "ET",
            "XK"
          ],
          "external_urls": {
            "spotify": "https://open.spotify.com/album/5lJqux7orBlA1QzyiBGti1"
          },
          "href": "https://api.spotify.com/v1/albums/5lJqux7orBlA1QzyiBGti1",
          "id": "5lJqux7orBlA1QzyiBGti1",
          "images": [
            {
              "height": 640,
              "url": "https://i.scdn.co/image/ab67616d0000b273548f7ec52da7313de0c5e4a0",
              "width": 640
            },
            {
              "height": 300,
              "url": "https://i.scdn.co/image/ab67616d00001e02548f7ec52da7313de0c5e4a0",
              "width": 300
            },
            {
              "height": 64,
              "url": "https://i.scdn.co/image/ab67616d00004851548f7ec52da7313de0c5e4a0",
              "width": 64
            }
          ],
          "name": "YHLQMDLG",
          "release_date": "2020-02-29",
          "release_date_precision": "day",
          "total_tracks": 20,
          "type": "album",
          "uri": "spotify:album:5lJqux7orBlA1QzyiBGti1"
        },
        "artists": [
          {
            "external_urls": {
              "spotify": "https://open.spotify.com/artist/4q3ewBCX7sLwd24euuV69X"
            },
            "href": "https://api.spotify.com/v1/artists/4q3ewBCX7sLwd24euuV69X",
            "id": "4q3ewBCX7sLwd24euuV69X",
            "name": "Bad Bunny",
            "type": "artist",
            "uri": "spotify:artist:4q3ewBCX7sLwd24euuV69X"
          }
        ],
        "available_markets": [
          "AR",
          "AU",
          "AT",
          "BE",
          "BO",
          "BR",
          "BG",
          "CA",
          "CL",
          "CO",
          "CR",
          "CY",
          "CZ",
          "DK",
          "DO",
          "DE",
          "EC",
          "EE",
          "SV",
          "FI",
          "FR",
          "GR",
          "GT",
          "HN",
          "HK",
          "HU",
          "IS",
          "IE",
          "IT",
          "LV",
          "LT",
          "LU",
          "MY",
          "MT",
          "MX",
          "NL",
          "NZ",
          "NI",
          "NO",
          "PA",
          "PY",
          "PE",
          "PH",
          "PL",
          "PT",
          "SG",
          "SK",
          "ES",
          "SE",
          "CH",
          "TW",
          "TR",
          "UY",
          "US",
          "GB",
          "AD",
          "LI",
          "MC",
          "ID",
          "JP",
          "TH",
          "VN",
          "RO",
          "IL",
          "ZA",
          "SA",
          "AE",
          "BH",
          "QA",
          "OM",
          "KW",
          "EG",
          "MA",
          "DZ",
          "TN",
          "LB",
          "JO",
          "PS",
          "IN",
          "BY",
          "KZ",
          "MD",
          "UA",
          "AL",
          "BA",
          "HR",
          "ME",
          "MK",
          "RS",
          "SI",
          "KR",
          "BD",
          "PK",
          "LK",
          "GH",
          "KE",
          "NG",
          "TZ",
          "UG",
          "AG",
          "AM",
          "BS",
          "BB",
          "BZ",
          "BT",
          "BW",
          "BF",
          "CV",
          "CW",
          "DM",
          "FJ",
          "GM",
          "GE",
          "GD",
          "GW",
          "GY",
          "HT",
          "JM",
          "KI",
          "LS",
          "LR",
          "MW",
          "MV",
          "ML",
          "MH",
          "FM",
          "NA",
          "NR",
          "NE",
          "PW",
          "PG",
          "WS",
          "SM",
          "ST",
          "SN",
          "SC",
          "SL",
          "SB",
          "KN",
          "LC",
          "VC",
          "SR",
          "TL",
          "TO",
          "TT",
          "TV",
          "VU",
          "AZ",
          "BN",
          "BI",
          "KH",
          "CM",
          "TD",
          "KM",
          "GQ",
          "SZ",
          "GA",
          "GN",
          "KG",
          "LA",
          "MO",
          "MR",
          "MN",
          "NP",
          "RW",
          "TG",
          "UZ",
          "ZW",
          "BJ",
          "MG",
          "MU",
          "MZ",
          "AO",
          "CI",
          "DJ",
          "ZM",
          "CD",
          "CG",
          "IQ",
          "LY",
          "TJ",
          "VE",
          "ET",
          "XK"
        ],
        "disc_number": 1,
        "duration_ms": 170971,
        "explicit": false,
        "external_ids": {
          "isrc": "QM4TX2030842"
        },
        "external_urls": {
          "spotify": "https://open.spotify.com/track/41wtwzCZkXwpnakmwJ239F"
        },
        "href": "https://api.spotify.com/v1/tracks/41wtwzCZkXwpnakmwJ239F",
        "id": "41wtwzCZkXwpnakmwJ239F",
        "is_local": false,
        "name": "Si Veo a Tu Mamá",
        "popularity": 79,
        "preview_url": "https://p.scdn.co/mp3-preview/b48baafc0b7c1c56bfaa445e6feaab155f0638f1?cid=5a0ffed4bc0642d794ffd4ab473c1b8f",
        "track_number": 1,
        "type": "track",
        "uri": "spotify:track:41wtwzCZkXwpnakmwJ239F"
      },
      "played_at": "2023-10-09T22:11:56.035Z",
      "context": null
    },
    {
      "track": {
        "album": {
          "album_type": "single",
          "artists": [
            {
              "external_urls": {
                "spotify": "https://open.spotify.com/artist/54P0u0BOmRdmtEVPgcoZy0"
              },
              "href": "https://api.spotify.com/v1/artists/54P0u0BOmRdmtEVPgcoZy0",
              "id": "54P0u0BOmRdmtEVPgcoZy0",
              "name": "Golden Ganga",
              "type": "artist",
              "uri": "spotify:artist:54P0u0BOmRdmtEVPgcoZy0"
            },
            {
              "external_urls": {
                "spotify": "https://open.spotify.com/artist/0x2z4hugJaiGdTP0lzhxvO"
              },
              "href": "https://api.spotify.com/v1/artists/0x2z4hugJaiGdTP0lzhxvO",
              "id": "0x2z4hugJaiGdTP0lzhxvO",
              "name": "A.C.O",
              "type": "artist",
              "uri": "spotify:artist:0x2z4hugJaiGdTP0lzhxvO"
            },
            {
              "external_urls": {
                "spotify": "https://open.spotify.com/artist/5lYeiQxUTcGKVgAuTqbTeL"
              },
              "href": "https://api.spotify.com/v1/artists/5lYeiQxUTcGKVgAuTqbTeL",
              "id": "5lYeiQxUTcGKVgAuTqbTeL",
              "name": "Charles Ans",
              "type": "artist",
              "uri": "spotify:artist:5lYeiQxUTcGKVgAuTqbTeL"
            }
          ],
          "available_markets": [
            "AR",
            "AU",
            "AT",
            "BE",
            "BO",
            "BR",
            "BG",
            "CA",
            "CL",
            "CO",
            "CR",
            "CY",
            "CZ",
            "DK",
            "DO",
            "DE",
            "EC",
            "EE",
            "SV",
            "FI",
            "FR",
            "GR",
            "GT",
            "HN",
            "HK",
            "HU",
            "IS",
            "IE",
            "IT",
            "LV",
            "LT",
            "LU",
            "MY",
            "MT",
            "MX",
            "NL",
            "NZ",
            "NI",
            "NO",
            "PA",
            "PY",
            "PE",
            "PH",
            "PL",
            "PT",
            "SG",
            "SK",
            "ES",
            "SE",
            "CH",
            "TW",
            "TR",
            "UY",
            "US",
            "GB",
            "AD",
            "LI",
            "MC",
            "ID",
            "JP",
            "TH",
            "VN",
            "RO",
            "IL",
            "ZA",
            "SA",
            "AE",
            "BH",
            "QA",
            "OM",
            "KW",
            "EG",
            "MA",
            "DZ",
            "TN",
            "LB",
            "JO",
            "PS",
            "IN",
            "BY",
            "KZ",
            "MD",
            "UA",
            "AL",
            "BA",
            "HR",
            "ME",
            "MK",
            "RS",
            "SI",
            "KR",
            "BD",
            "PK",
            "LK",
            "GH",
            "KE",
            "NG",
            "TZ",
            "UG",
            "AG",
            "AM",
            "BS",
            "BB",
            "BZ",
            "BT",
            "BW",
            "BF",
            "CV",
            "CW",
            "DM",
            "FJ",
            "GM",
            "GE",
            "GD",
            "GW",
            "GY",
            "HT",
            "JM",
            "KI",
            "LS",
            "LR",
            "MW",
            "MV",
            "ML",
            "MH",
            "FM",
            "NA",
            "NR",
            "NE",
            "PW",
            "PG",
            "WS",
            "SM",
            "ST",
            "SN",
            "SC",
            "SL",
            "SB",
            "KN",
            "LC",
            "VC",
            "SR",
            "TL",
            "TO",
            "TT",
            "TV",
            "VU",
            "AZ",
            "BN",
            "BI",
            "KH",
            "CM",
            "TD",
            "KM",
            "GQ",
            "SZ",
            "GA",
            "GN",
            "KG",
            "LA",
            "MO",
            "MR",
            "MN",
            "NP",
            "RW",
            "TG",
            "UZ",
            "ZW",
            "BJ",
            "MG",
            "MU",
            "MZ",
            "AO",
            "CI",
            "DJ",
            "ZM",
            "CD",
            "CG",
            "IQ",
            "LY",
            "TJ",
            "VE",
            "ET",
            "XK"
          ],
          "external_urls": {
            "spotify": "https://open.spotify.com/album/0jDAxF4M0RxVNM5JUJCiwX"
          },
          "href": "https://api.spotify.com/v1/albums/0jDAxF4M0RxVNM5JUJCiwX",
          "id": "0jDAxF4M0RxVNM5JUJCiwX",
          "images": [
            {
              "height": 640,
              "url": "https://i.scdn.co/image/ab67616d0000b273f59fd0c802ab4e906e1ca834",
              "width": 640
            },
            {
              "height": 300,
              "url": "https://i.scdn.co/image/ab67616d00001e02f59fd0c802ab4e906e1ca834",
              "width": 300
            },
            {
              "height": 64,
              "url": "https://i.scdn.co/image/ab67616d00004851f59fd0c802ab4e906e1ca834",
              "width": 64
            }
          ],
          "name": "ALGO BIEN",
          "release_date": "2020-10-23",
          "release_date_precision": "day",
          "total_tracks": 1,
          "type": "album",
          "uri": "spotify:album:0jDAxF4M0RxVNM5JUJCiwX"
        },
        "artists": [
          {
            "external_urls": {
              "spotify": "https://open.spotify.com/artist/54P0u0BOmRdmtEVPgcoZy0"
            },
            "href": "https://api.spotify.com/v1/artists/54P0u0BOmRdmtEVPgcoZy0",
            "id": "54P0u0BOmRdmtEVPgcoZy0",
            "name": "Golden Ganga",
            "type": "artist",
            "uri": "spotify:artist:54P0u0BOmRdmtEVPgcoZy0"
          },
          {
            "external_urls": {
              "spotify": "https://open.spotify.com/artist/5lYeiQxUTcGKVgAuTqbTeL"
            },
            "href": "https://api.spotify.com/v1/artists/5lYeiQxUTcGKVgAuTqbTeL",
            "id": "5lYeiQxUTcGKVgAuTqbTeL",
            "name": "Charles Ans",
            "type": "artist",
            "uri": "spotify:artist:5lYeiQxUTcGKVgAuTqbTeL"
          },
          {
            "external_urls": {
              "spotify": "https://open.spotify.com/artist/0x2z4hugJaiGdTP0lzhxvO"
            },
            "href": "https://api.spotify.com/v1/artists/0x2z4hugJaiGdTP0lzhxvO",
            "id": "0x2z4hugJaiGdTP0lzhxvO",
            "name": "A.C.O",
            "type": "artist",
            "uri": "spotify:artist:0x2z4hugJaiGdTP0lzhxvO"
          },
          {
            "external_urls": {
              "spotify": "https://open.spotify.com/artist/307pYxWsFHn3u9gMe8vaf3"
            },
            "href": "https://api.spotify.com/v1/artists/307pYxWsFHn3u9gMe8vaf3",
            "id": "307pYxWsFHn3u9gMe8vaf3",
            "name": "Rafael Lechowski",
            "type": "artist",
            "uri": "spotify:artist:307pYxWsFHn3u9gMe8vaf3"
          }
        ],
        "available_markets": [
          "AR",
          "AU",
          "AT",
          "BE",
          "BO",
          "BR",
          "BG",
          "CA",
          "CL",
          "CO",
          "CR",
          "CY",
          "CZ",
          "DK",
          "DO",
          "DE",
          "EC",
          "EE",
          "SV",
          "FI",
          "FR",
          "GR",
          "GT",
          "HN",
          "HK",
          "HU",
          "IS",
          "IE",
          "IT",
          "LV",
          "LT",
          "LU",
          "MY",
          "MT",
          "MX",
          "NL",
          "NZ",
          "NI",
          "NO",
          "PA",
          "PY",
          "PE",
          "PH",
          "PL",
          "PT",
          "SG",
          "SK",
          "ES",
          "SE",
          "CH",
          "TW",
          "TR",
          "UY",
          "US",
          "GB",
          "AD",
          "LI",
          "MC",
          "ID",
          "JP",
          "TH",
          "VN",
          "RO",
          "IL",
          "ZA",
          "SA",
          "AE",
          "BH",
          "QA",
          "OM",
          "KW",
          "EG",
          "MA",
          "DZ",
          "TN",
          "LB",
          "JO",
          "PS",
          "IN",
          "BY",
          "KZ",
          "MD",
          "UA",
          "AL",
          "BA",
          "HR",
          "ME",
          "MK",
          "RS",
          "SI",
          "KR",
          "BD",
          "PK",
          "LK",
          "GH",
          "KE",
          "NG",
          "TZ",
          "UG",
          "AG",
          "AM",
          "BS",
          "BB",
          "BZ",
          "BT",
          "BW",
          "BF",
          "CV",
          "CW",
          "DM",
          "FJ",
          "GM",
          "GE",
          "GD",
          "GW",
          "GY",
          "HT",
          "JM",
          "KI",
          "LS",
          "LR",
          "MW",
          "MV",
          "ML",
          "MH",
          "FM",
          "NA",
          "NR",
          "NE",
          "PW",
          "PG",
          "WS",
          "SM",
          "ST",
          "SN",
          "SC",
          "SL",
          "SB",
          "KN",
          "LC",
          "VC",
          "SR",
          "TL",
          "TO",
          "TT",
          "TV",
          "VU",
          "AZ",
          "BN",
          "BI",
          "KH",
          "CM",
          "TD",
          "KM",
          "GQ",
          "SZ",
          "GA",
          "GN",
          "KG",
          "LA",
          "MO",
          "MR",
          "MN",
          "NP",
          "RW",
          "TG",
          "UZ",
          "ZW",
          "BJ",
          "MG",
          "MU",
          "MZ",
          "AO",
          "CI",
          "DJ",
          "ZM",
          "CD",
          "CG",
          "IQ",
          "LY",
          "TJ",
          "VE",
          "ET",
          "XK"
        ],
        "disc_number": 1,
        "duration_ms": 271058,
        "explicit": true,
        "external_ids": {
          "isrc": "QZNJV2067893"
        },
        "external_urls": {
          "spotify": "https://open.spotify.com/track/77jU7HYCU4jQUPIGqqNS5e"
        },
        "href": "https://api.spotify.com/v1/tracks/77jU7HYCU4jQUPIGqqNS5e",
        "id": "77jU7HYCU4jQUPIGqqNS5e",
        "is_local": false,
        "name": "ALGO BIEN",
        "popularity": 47,
        "preview_url": "https://p.scdn.co/mp3-preview/8feb27ace7d253c54bda6da88ea5b474944db0e7?cid=5a0ffed4bc0642d794ffd4ab473c1b8f",
        "track_number": 1,
        "type": "track",
        "uri": "spotify:track:77jU7HYCU4jQUPIGqqNS5e"
      },
      "played_at": "2023-10-09T22:09:03.994Z",
      "context": null
    },
    {
      "track": {
        "album": {
          "album_type": "album",
          "artists": [
            {
              "external_urls": {
                "spotify": "https://open.spotify.com/artist/1FCItwxfRieMGhR0eRxotU"
              },
              "href": "https://api.spotify.com/v1/artists/1FCItwxfRieMGhR0eRxotU",
              "id": "1FCItwxfRieMGhR0eRxotU",
              "name": "Rich Vagos",
              "type": "artist",
              "uri": "spotify:artist:1FCItwxfRieMGhR0eRxotU"
            }
          ],
          "available_markets": [
            "AR",
            "AU",
            "AT",
            "BE",
            "BO",
            "BR",
            "BG",
            "CA",
            "CL",
            "CO",
            "CR",
            "CY",
            "CZ",
            "DK",
            "DO",
            "DE",
            "EC",
            "EE",
            "SV",
            "FI",
            "FR",
            "GR",
            "GT",
            "HN",
            "HK",
            "HU",
            "IS",
            "IE",
            "IT",
            "LV",
            "LT",
            "LU",
            "MY",
            "MT",
            "MX",
            "NL",
            "NZ",
            "NI",
            "NO",
            "PA",
            "PY",
            "PE",
            "PH",
            "PL",
            "PT",
            "SG",
            "SK",
            "ES",
            "SE",
            "CH",
            "TW",
            "TR",
            "UY",
            "US",
            "GB",
            "AD",
            "LI",
            "MC",
            "ID",
            "JP",
            "TH",
            "VN",
            "RO",
            "IL",
            "ZA",
            "SA",
            "AE",
            "BH",
            "QA",
            "OM",
            "KW",
            "EG",
            "MA",
            "DZ",
            "TN",
            "LB",
            "JO",
            "PS",
            "IN",
            "BY",
            "KZ",
            "MD",
            "UA",
            "AL",
            "BA",
            "HR",
            "ME",
            "MK",
            "RS",
            "SI",
            "KR",
            "BD",
            "PK",
            "LK",
            "GH",
            "KE",
            "NG",
            "TZ",
            "UG",
            "AG",
            "AM",
            "BS",
            "BB",
            "BZ",
            "BT",
            "BW",
            "BF",
            "CV",
            "CW",
            "DM",
            "FJ",
            "GM",
            "GE",
            "GD",
            "GW",
            "GY",
            "HT",
            "JM",
            "KI",
            "LS",
            "LR",
            "MW",
            "MV",
            "ML",
            "MH",
            "FM",
            "NA",
            "NR",
            "NE",
            "PW",
            "PG",
            "WS",
            "SM",
            "ST",
            "SN",
            "SC",
            "SL",
            "SB",
            "KN",
            "LC",
            "VC",
            "SR",
            "TL",
            "TO",
            "TT",
            "TV",
            "VU",
            "AZ",
            "BN",
            "BI",
            "KH",
            "CM",
            "TD",
            "KM",
            "GQ",
            "SZ",
            "GA",
            "GN",
            "KG",
            "LA",
            "MO",
            "MR",
            "MN",
            "NP",
            "RW",
            "TG",
            "UZ",
            "ZW",
            "BJ",
            "MG",
            "MU",
            "MZ",
            "AO",
            "CI",
            "DJ",
            "ZM",
            "CD",
            "CG",
            "IQ",
            "LY",
            "TJ",
            "VE",
            "ET",
            "XK"
          ],
          "external_urls": {
            "spotify": "https://open.spotify.com/album/2kGTwHezbLOPc7wK5YLVL7"
          },
          "href": "https://api.spotify.com/v1/albums/2kGTwHezbLOPc7wK5YLVL7",
          "id": "2kGTwHezbLOPc7wK5YLVL7",
          "images": [
            {
              "height": 640,
              "url": "https://i.scdn.co/image/ab67616d0000b27355ea09f0a8947065473e8f45",
              "width": 640
            },
            {
              "height": 300,
              "url": "https://i.scdn.co/image/ab67616d00001e0255ea09f0a8947065473e8f45",
              "width": 300
            },
            {
              "height": 64,
              "url": "https://i.scdn.co/image/ab67616d0000485155ea09f0a8947065473e8f45",
              "width": 64
            }
          ],
          "name": "Rich Vagos Mixtape, Vol. 2",
          "release_date": "2022-11-18",
          "release_date_precision": "day",
          "total_tracks": 29,
          "type": "album",
          "uri": "spotify:album:2kGTwHezbLOPc7wK5YLVL7"
        },
        "artists": [
          {
            "external_urls": {
              "spotify": "https://open.spotify.com/artist/1FCItwxfRieMGhR0eRxotU"
            },
            "href": "https://api.spotify.com/v1/artists/1FCItwxfRieMGhR0eRxotU",
            "id": "1FCItwxfRieMGhR0eRxotU",
            "name": "Rich Vagos",
            "type": "artist",
            "uri": "spotify:artist:1FCItwxfRieMGhR0eRxotU"
          },
          {
            "external_urls": {
              "spotify": "https://open.spotify.com/artist/2hejA1Dkf8v8R0koF44FvW"
            },
            "href": "https://api.spotify.com/v1/artists/2hejA1Dkf8v8R0koF44FvW",
            "id": "2hejA1Dkf8v8R0koF44FvW",
            "name": "Gera MX",
            "type": "artist",
            "uri": "spotify:artist:2hejA1Dkf8v8R0koF44FvW"
          },
          {
            "external_urls": {
              "spotify": "https://open.spotify.com/artist/0U8dIwzBn17JkhYxmznp6T"
            },
            "href": "https://api.spotify.com/v1/artists/0U8dIwzBn17JkhYxmznp6T",
            "id": "0U8dIwzBn17JkhYxmznp6T",
            "name": "Jayrick",
            "type": "artist",
            "uri": "spotify:artist:0U8dIwzBn17JkhYxmznp6T"
          }
        ],
        "available_markets": [
          "AR",
          "AU",
          "AT",
          "BE",
          "BO",
          "BR",
          "BG",
          "CA",
          "CL",
          "CO",
          "CR",
          "CY",
          "CZ",
          "DK",
          "DO",
          "DE",
          "EC",
          "EE",
          "SV",
          "FI",
          "FR",
          "GR",
          "GT",
          "HN",
          "HK",
          "HU",
          "IS",
          "IE",
          "IT",
          "LV",
          "LT",
          "LU",
          "MY",
          "MT",
          "MX",
          "NL",
          "NZ",
          "NI",
          "NO",
          "PA",
          "PY",
          "PE",
          "PH",
          "PL",
          "PT",
          "SG",
          "SK",
          "ES",
          "SE",
          "CH",
          "TW",
          "TR",
          "UY",
          "US",
          "GB",
          "AD",
          "LI",
          "MC",
          "ID",
          "JP",
          "TH",
          "VN",
          "RO",
          "IL",
          "ZA",
          "SA",
          "AE",
          "BH",
          "QA",
          "OM",
          "KW",
          "EG",
          "MA",
          "DZ",
          "TN",
          "LB",
          "JO",
          "PS",
          "IN",
          "BY",
          "KZ",
          "MD",
          "UA",
          "AL",
          "BA",
          "HR",
          "ME",
          "MK",
          "RS",
          "SI",
          "KR",
          "BD",
          "PK",
          "LK",
          "GH",
          "KE",
          "NG",
          "TZ",
          "UG",
          "AG",
          "AM",
          "BS",
          "BB",
          "BZ",
          "BT",
          "BW",
          "BF",
          "CV",
          "CW",
          "DM",
          "FJ",
          "GM",
          "GE",
          "GD",
          "GW",
          "GY",
          "HT",
          "JM",
          "KI",
          "LS",
          "LR",
          "MW",
          "MV",
          "ML",
          "MH",
          "FM",
          "NA",
          "NR",
          "NE",
          "PW",
          "PG",
          "WS",
          "SM",
          "ST",
          "SN",
          "SC",
          "SL",
          "SB",
          "KN",
          "LC",
          "VC",
          "SR",
          "TL",
          "TO",
          "TT",
          "TV",
          "VU",
          "AZ",
          "BN",
          "BI",
          "KH",
          "CM",
          "TD",
          "KM",
          "GQ",
          "SZ",
          "GA",
          "GN",
          "KG",
          "LA",
          "MO",
          "MR",
          "MN",
          "NP",
          "RW",
          "TG",
          "UZ",
          "ZW",
          "BJ",
          "MG",
          "MU",
          "MZ",
          "AO",
          "CI",
          "DJ",
          "ZM",
          "CD",
          "CG",
          "IQ",
          "LY",
          "TJ",
          "VE",
          "ET",
          "XK"
        ],
        "disc_number": 1,
        "duration_ms": 158300,
        "explicit": false,
        "external_ids": {
          "isrc": "QZW9K2267238"
        },
        "external_urls": {
          "spotify": "https://open.spotify.com/track/1MEFrBlkxaX088SRCStDX7"
        },
        "href": "https://api.spotify.com/v1/tracks/1MEFrBlkxaX088SRCStDX7",
        "id": "1MEFrBlkxaX088SRCStDX7",
        "is_local": false,
        "name": "Bendecido",
        "popularity": 44,
        "preview_url": "https://p.scdn.co/mp3-preview/73a0ef9fdc52308e43d25834250a3a9dd65dfdf2?cid=5a0ffed4bc0642d794ffd4ab473c1b8f",
        "track_number": 1,
        "type": "track",
        "uri": "spotify:track:1MEFrBlkxaX088SRCStDX7"
      },
      "played_at": "2023-10-09T22:04:32.998Z",
      "context": null
    },
    {
      "track": {
        "album": {
          "album_type": "single",
          "artists": [
            {
              "external_urls": {
                "spotify": "https://open.spotify.com/artist/5lYeiQxUTcGKVgAuTqbTeL"
              },
              "href": "https://api.spotify.com/v1/artists/5lYeiQxUTcGKVgAuTqbTeL",
              "id": "5lYeiQxUTcGKVgAuTqbTeL",
              "name": "Charles Ans",
              "type": "artist",
              "uri": "spotify:artist:5lYeiQxUTcGKVgAuTqbTeL"
            },
            {
              "external_urls": {
                "spotify": "https://open.spotify.com/artist/1cUpGtXcSQsovNYEZOQgOG"
              },
              "href": "https://api.spotify.com/v1/artists/1cUpGtXcSQsovNYEZOQgOG",
              "id": "1cUpGtXcSQsovNYEZOQgOG",
              "name": "Nanpa Básico",
              "type": "artist",
              "uri": "spotify:artist:1cUpGtXcSQsovNYEZOQgOG"
            },
            {
              "external_urls": {
                "spotify": "https://open.spotify.com/artist/5pIapcAHb6WV4fUjfQchMf"
              },
              "href": "https://api.spotify.com/v1/artists/5pIapcAHb6WV4fUjfQchMf",
              "id": "5pIapcAHb6WV4fUjfQchMf",
              "name": "Sharif",
              "type": "artist",
              "uri": "spotify:artist:5pIapcAHb6WV4fUjfQchMf"
            }
          ],
          "available_markets": [
            "AR",
            "AU",
            "AT",
            "BE",
            "BO",
            "BR",
            "BG",
            "CA",
            "CL",
            "CO",
            "CR",
            "CY",
            "CZ",
            "DK",
            "DO",
            "DE",
            "EC",
            "EE",
            "SV",
            "FI",
            "FR",
            "GR",
            "GT",
            "HN",
            "HK",
            "HU",
            "IS",
            "IE",
            "IT",
            "LV",
            "LT",
            "LU",
            "MY",
            "MT",
            "MX",
            "NL",
            "NZ",
            "NI",
            "NO",
            "PA",
            "PY",
            "PE",
            "PH",
            "PL",
            "PT",
            "SG",
            "SK",
            "ES",
            "SE",
            "CH",
            "TW",
            "TR",
            "UY",
            "US",
            "GB",
            "AD",
            "LI",
            "MC",
            "ID",
            "JP",
            "TH",
            "VN",
            "RO",
            "IL",
            "ZA",
            "SA",
            "AE",
            "BH",
            "QA",
            "OM",
            "KW",
            "EG",
            "MA",
            "DZ",
            "TN",
            "LB",
            "JO",
            "PS",
            "IN",
            "BY",
            "KZ",
            "MD",
            "UA",
            "AL",
            "BA",
            "HR",
            "ME",
            "MK",
            "RS",
            "SI",
            "KR",
            "BD",
            "PK",
            "LK",
            "GH",
            "KE",
            "NG",
            "TZ",
            "UG",
            "AG",
            "AM",
            "BS",
            "BB",
            "BZ",
            "BT",
            "BW",
            "BF",
            "CV",
            "CW",
            "DM",
            "FJ",
            "GM",
            "GE",
            "GD",
            "GW",
            "GY",
            "HT",
            "JM",
            "KI",
            "LS",
            "LR",
            "MW",
            "MV",
            "ML",
            "MH",
            "FM",
            "NA",
            "NR",
            "NE",
            "PW",
            "PG",
            "WS",
            "SM",
            "ST",
            "SN",
            "SC",
            "SL",
            "SB",
            "KN",
            "LC",
            "VC",
            "SR",
            "TL",
            "TO",
            "TT",
            "TV",
            "VU",
            "AZ",
            "BN",
            "BI",
            "KH",
            "CM",
            "TD",
            "KM",
            "GQ",
            "SZ",
            "GA",
            "GN",
            "KG",
            "LA",
            "MO",
            "MR",
            "MN",
            "NP",
            "RW",
            "TG",
            "UZ",
            "ZW",
            "BJ",
            "MG",
            "MU",
            "MZ",
            "AO",
            "CI",
            "DJ",
            "ZM",
            "CD",
            "CG",
            "IQ",
            "LY",
            "TJ",
            "VE",
            "ET",
            "XK"
          ],
          "external_urls": {
            "spotify": "https://open.spotify.com/album/74h1UctdpODA4PIm2Bq4J6"
          },
          "href": "https://api.spotify.com/v1/albums/74h1UctdpODA4PIm2Bq4J6",
          "id": "74h1UctdpODA4PIm2Bq4J6",
          "images": [
            {
              "height": 640,
              "url": "https://i.scdn.co/image/ab67616d0000b273d761eeb45162a8e99d29650f",
              "width": 640
            },
            {
              "height": 300,
              "url": "https://i.scdn.co/image/ab67616d00001e02d761eeb45162a8e99d29650f",
              "width": 300
            },
            {
              "height": 64,
              "url": "https://i.scdn.co/image/ab67616d00004851d761eeb45162a8e99d29650f",
              "width": 64
            }
          ],
          "name": "En Lo Malo Me Va Bien",
          "release_date": "2021-11-26",
          "release_date_precision": "day",
          "total_tracks": 1,
          "type": "album",
          "uri": "spotify:album:74h1UctdpODA4PIm2Bq4J6"
        },
        "artists": [
          {
            "external_urls": {
              "spotify": "https://open.spotify.com/artist/5lYeiQxUTcGKVgAuTqbTeL"
            },
            "href": "https://api.spotify.com/v1/artists/5lYeiQxUTcGKVgAuTqbTeL",
            "id": "5lYeiQxUTcGKVgAuTqbTeL",
            "name": "Charles Ans",
            "type": "artist",
            "uri": "spotify:artist:5lYeiQxUTcGKVgAuTqbTeL"
          },
          {
            "external_urls": {
              "spotify": "https://open.spotify.com/artist/1cUpGtXcSQsovNYEZOQgOG"
            },
            "href": "https://api.spotify.com/v1/artists/1cUpGtXcSQsovNYEZOQgOG",
            "id": "1cUpGtXcSQsovNYEZOQgOG",
            "name": "Nanpa Básico",
            "type": "artist",
            "uri": "spotify:artist:1cUpGtXcSQsovNYEZOQgOG"
          },
          {
            "external_urls": {
              "spotify": "https://open.spotify.com/artist/5pIapcAHb6WV4fUjfQchMf"
            },
            "href": "https://api.spotify.com/v1/artists/5pIapcAHb6WV4fUjfQchMf",
            "id": "5pIapcAHb6WV4fUjfQchMf",
            "name": "Sharif",
            "type": "artist",
            "uri": "spotify:artist:5pIapcAHb6WV4fUjfQchMf"
          },
          {
            "external_urls": {
              "spotify": "https://open.spotify.com/artist/1M3oDOCXXZVkIlXPp5gAKd"
            },
            "href": "https://api.spotify.com/v1/artists/1M3oDOCXXZVkIlXPp5gAKd",
            "id": "1M3oDOCXXZVkIlXPp5gAKd",
            "name": "BCN",
            "type": "artist",
            "uri": "spotify:artist:1M3oDOCXXZVkIlXPp5gAKd"
          }
        ],
        "available_markets": [
          "AR",
          "AU",
          "AT",
          "BE",
          "BO",
          "BR",
          "BG",
          "CA",
          "CL",
          "CO",
          "CR",
          "CY",
          "CZ",
          "DK",
          "DO",
          "DE",
          "EC",
          "EE",
          "SV",
          "FI",
          "FR",
          "GR",
          "GT",
          "HN",
          "HK",
          "HU",
          "IS",
          "IE",
          "IT",
          "LV",
          "LT",
          "LU",
          "MY",
          "MT",
          "MX",
          "NL",
          "NZ",
          "NI",
          "NO",
          "PA",
          "PY",
          "PE",
          "PH",
          "PL",
          "PT",
          "SG",
          "SK",
          "ES",
          "SE",
          "CH",
          "TW",
          "TR",
          "UY",
          "US",
          "GB",
          "AD",
          "LI",
          "MC",
          "ID",
          "JP",
          "TH",
          "VN",
          "RO",
          "IL",
          "ZA",
          "SA",
          "AE",
          "BH",
          "QA",
          "OM",
          "KW",
          "EG",
          "MA",
          "DZ",
          "TN",
          "LB",
          "JO",
          "PS",
          "IN",
          "BY",
          "KZ",
          "MD",
          "UA",
          "AL",
          "BA",
          "HR",
          "ME",
          "MK",
          "RS",
          "SI",
          "KR",
          "BD",
          "PK",
          "LK",
          "GH",
          "KE",
          "NG",
          "TZ",
          "UG",
          "AG",
          "AM",
          "BS",
          "BB",
          "BZ",
          "BT",
          "BW",
          "BF",
          "CV",
          "CW",
          "DM",
          "FJ",
          "GM",
          "GE",
          "GD",
          "GW",
          "GY",
          "HT",
          "JM",
          "KI",
          "LS",
          "LR",
          "MW",
          "MV",
          "ML",
          "MH",
          "FM",
          "NA",
          "NR",
          "NE",
          "PW",
          "PG",
          "WS",
          "SM",
          "ST",
          "SN",
          "SC",
          "SL",
          "SB",
          "KN",
          "LC",
          "VC",
          "SR",
          "TL",
          "TO",
          "TT",
          "TV",
          "VU",
          "AZ",
          "BN",
          "BI",
          "KH",
          "CM",
          "TD",
          "KM",
          "GQ",
          "SZ",
          "GA",
          "GN",
          "KG",
          "LA",
          "MO",
          "MR",
          "MN",
          "NP",
          "RW",
          "TG",
          "UZ",
          "ZW",
          "BJ",
          "MG",
          "MU",
          "MZ",
          "AO",
          "CI",
          "DJ",
          "ZM",
          "CD",
          "CG",
          "IQ",
          "LY",
          "TJ",
          "VE",
          "ET",
          "XK"
        ],
        "disc_number": 1,
        "duration_ms": 241000,
        "explicit": true,
        "external_ids": {
          "isrc": "QZNJY2136557"
        },
        "external_urls": {
          "spotify": "https://open.spotify.com/track/6ylcwUZcs28IZEfayrpVcH"
        },
        "href": "https://api.spotify.com/v1/tracks/6ylcwUZcs28IZEfayrpVcH",
        "id": "6ylcwUZcs28IZEfayrpVcH",
        "is_local": false,
        "name": "En Lo Malo Me Va Bien",
        "popularity": 33,
        "preview_url": "https://p.scdn.co/mp3-preview/da009031c5f8454f251384fddb4f0617d0eb993a?cid=5a0ffed4bc0642d794ffd4ab473c1b8f",
        "track_number": 1,
        "type": "track",
        "uri": "spotify:track:6ylcwUZcs28IZEfayrpVcH"
      },
      "played_at": "2023-10-09T22:01:53.863Z",
      "context": null
    },
    {
      "track": {
        "album": {
          "album_type": "album",
          "artists": [
            {
              "external_urls": {
                "spotify": "https://open.spotify.com/artist/4V2V4PaSblStayYVWTGDbZ"
              },
              "href": "https://api.spotify.com/v1/artists/4V2V4PaSblStayYVWTGDbZ",
              "id": "4V2V4PaSblStayYVWTGDbZ",
              "name": "Geassassin",
              "type": "artist",
              "uri": "spotify:artist:4V2V4PaSblStayYVWTGDbZ"
            }
          ],
          "available_markets": [
            "AR",
            "AU",
            "AT",
            "BE",
            "BO",
            "BR",
            "BG",
            "CA",
            "CL",
            "CO",
            "CR",
            "CY",
            "CZ",
            "DK",
            "DO",
            "DE",
            "EC",
            "EE",
            "SV",
            "FI",
            "FR",
            "GR",
            "GT",
            "HN",
            "HK",
            "HU",
            "IS",
            "IE",
            "IT",
            "LV",
            "LT",
            "LU",
            "MY",
            "MT",
            "MX",
            "NL",
            "NZ",
            "NI",
            "NO",
            "PA",
            "PY",
            "PE",
            "PH",
            "PL",
            "PT",
            "SG",
            "SK",
            "ES",
            "SE",
            "CH",
            "TW",
            "TR",
            "UY",
            "US",
            "GB",
            "AD",
            "LI",
            "MC",
            "ID",
            "JP",
            "TH",
            "VN",
            "RO",
            "IL",
            "ZA",
            "SA",
            "AE",
            "BH",
            "QA",
            "OM",
            "KW",
            "EG",
            "MA",
            "DZ",
            "TN",
            "LB",
            "JO",
            "PS",
            "IN",
            "BY",
            "KZ",
            "MD",
            "UA",
            "AL",
            "BA",
            "HR",
            "ME",
            "MK",
            "RS",
            "SI",
            "KR",
            "BD",
            "PK",
            "LK",
            "GH",
            "KE",
            "NG",
            "TZ",
            "UG",
            "AG",
            "AM",
            "BS",
            "BB",
            "BZ",
            "BT",
            "BW",
            "BF",
            "CV",
            "CW",
            "DM",
            "FJ",
            "GM",
            "GE",
            "GD",
            "GW",
            "GY",
            "HT",
            "JM",
            "KI",
            "LS",
            "LR",
            "MW",
            "MV",
            "ML",
            "MH",
            "FM",
            "NA",
            "NR",
            "NE",
            "PW",
            "PG",
            "WS",
            "SM",
            "ST",
            "SN",
            "SC",
            "SL",
            "SB",
            "KN",
            "LC",
            "VC",
            "SR",
            "TL",
            "TO",
            "TT",
            "TV",
            "VU",
            "AZ",
            "BN",
            "BI",
            "KH",
            "CM",
            "TD",
            "KM",
            "GQ",
            "SZ",
            "GA",
            "GN",
            "KG",
            "LA",
            "MO",
            "MR",
            "MN",
            "NP",
            "RW",
            "TG",
            "UZ",
            "ZW",
            "BJ",
            "MG",
            "MU",
            "MZ",
            "AO",
            "CI",
            "DJ",
            "ZM",
            "CD",
            "CG",
            "IQ",
            "LY",
            "TJ",
            "VE",
            "ET",
            "XK"
          ],
          "external_urls": {
            "spotify": "https://open.spotify.com/album/6RBGm1BTZmgxk7kCiTHvNB"
          },
          "href": "https://api.spotify.com/v1/albums/6RBGm1BTZmgxk7kCiTHvNB",
          "id": "6RBGm1BTZmgxk7kCiTHvNB",
          "images": [
            {
              "height": 640,
              "url": "https://i.scdn.co/image/ab67616d0000b2739340c6cb93d104d5e2ada82a",
              "width": 640
            },
            {
              "height": 300,
              "url": "https://i.scdn.co/image/ab67616d00001e029340c6cb93d104d5e2ada82a",
              "width": 300
            },
            {
              "height": 64,
              "url": "https://i.scdn.co/image/ab67616d000048519340c6cb93d104d5e2ada82a",
              "width": 64
            }
          ],
          "name": "El Nuevo Leon",
          "release_date": "2020-12-16",
          "release_date_precision": "day",
          "total_tracks": 10,
          "type": "album",
          "uri": "spotify:album:6RBGm1BTZmgxk7kCiTHvNB"
        },
        "artists": [
          {
            "external_urls": {
              "spotify": "https://open.spotify.com/artist/4V2V4PaSblStayYVWTGDbZ"
            },
            "href": "https://api.spotify.com/v1/artists/4V2V4PaSblStayYVWTGDbZ",
            "id": "4V2V4PaSblStayYVWTGDbZ",
            "name": "Geassassin",
            "type": "artist",
            "uri": "spotify:artist:4V2V4PaSblStayYVWTGDbZ"
          }
        ],
        "available_markets": [
          "AR",
          "AU",
          "AT",
          "BE",
          "BO",
          "BR",
          "BG",
          "CA",
          "CL",
          "CO",
          "CR",
          "CY",
          "CZ",
          "DK",
          "DO",
          "DE",
          "EC",
          "EE",
          "SV",
          "FI",
          "FR",
          "GR",
          "GT",
          "HN",
          "HK",
          "HU",
          "IS",
          "IE",
          "IT",
          "LV",
          "LT",
          "LU",
          "MY",
          "MT",
          "MX",
          "NL",
          "NZ",
          "NI",
          "NO",
          "PA",
          "PY",
          "PE",
          "PH",
          "PL",
          "PT",
          "SG",
          "SK",
          "ES",
          "SE",
          "CH",
          "TW",
          "TR",
          "UY",
          "US",
          "GB",
          "AD",
          "LI",
          "MC",
          "ID",
          "JP",
          "TH",
          "VN",
          "RO",
          "IL",
          "ZA",
          "SA",
          "AE",
          "BH",
          "QA",
          "OM",
          "KW",
          "EG",
          "MA",
          "DZ",
          "TN",
          "LB",
          "JO",
          "PS",
          "IN",
          "BY",
          "KZ",
          "MD",
          "UA",
          "AL",
          "BA",
          "HR",
          "ME",
          "MK",
          "RS",
          "SI",
          "KR",
          "BD",
          "PK",
          "LK",
          "GH",
          "KE",
          "NG",
          "TZ",
          "UG",
          "AG",
          "AM",
          "BS",
          "BB",
          "BZ",
          "BT",
          "BW",
          "BF",
          "CV",
          "CW",
          "DM",
          "FJ",
          "GM",
          "GE",
          "GD",
          "GW",
          "GY",
          "HT",
          "JM",
          "KI",
          "LS",
          "LR",
          "MW",
          "MV",
          "ML",
          "MH",
          "FM",
          "NA",
          "NR",
          "NE",
          "PW",
          "PG",
          "WS",
          "SM",
          "ST",
          "SN",
          "SC",
          "SL",
          "SB",
          "KN",
          "LC",
          "VC",
          "SR",
          "TL",
          "TO",
          "TT",
          "TV",
          "VU",
          "AZ",
          "BN",
          "BI",
          "KH",
          "CM",
          "TD",
          "KM",
          "GQ",
          "SZ",
          "GA",
          "GN",
          "KG",
          "LA",
          "MO",
          "MR",
          "MN",
          "NP",
          "RW",
          "TG",
          "UZ",
          "ZW",
          "BJ",
          "MG",
          "MU",
          "MZ",
          "AO",
          "CI",
          "DJ",
          "ZM",
          "CD",
          "CG",
          "IQ",
          "LY",
          "TJ",
          "VE",
          "ET",
          "XK"
        ],
        "disc_number": 1,
        "duration_ms": 225000,
        "explicit": false,
        "external_ids": {
          "isrc": "DGA052013349"
        },
        "external_urls": {
          "spotify": "https://open.spotify.com/track/5uowWtLHwNToA3o2TeHIJI"
        },
        "href": "https://api.spotify.com/v1/tracks/5uowWtLHwNToA3o2TeHIJI",
        "id": "5uowWtLHwNToA3o2TeHIJI",
        "is_local": false,
        "name": "Cool",
        "popularity": 27,
        "preview_url": "https://p.scdn.co/mp3-preview/bac4e42a8a741863b9929e2ce107bf6861df4b4e?cid=5a0ffed4bc0642d794ffd4ab473c1b8f",
        "track_number": 2,
        "type": "track",
        "uri": "spotify:track:5uowWtLHwNToA3o2TeHIJI"
      },
      "played_at": "2023-10-09T21:57:52.183Z",
      "context": null
    },
    {
      "track": {
        "album": {
          "album_type": "album",
          "artists": [
            {
              "external_urls": {
                "spotify": "https://open.spotify.com/artist/4V2V4PaSblStayYVWTGDbZ"
              },
              "href": "https://api.spotify.com/v1/artists/4V2V4PaSblStayYVWTGDbZ",
              "id": "4V2V4PaSblStayYVWTGDbZ",
              "name": "Geassassin",
              "type": "artist",
              "uri": "spotify:artist:4V2V4PaSblStayYVWTGDbZ"
            }
          ],
          "available_markets": [
            "AR",
            "AU",
            "AT",
            "BE",
            "BO",
            "BR",
            "BG",
            "CA",
            "CL",
            "CO",
            "CR",
            "CY",
            "CZ",
            "DK",
            "DO",
            "DE",
            "EC",
            "EE",
            "SV",
            "FI",
            "FR",
            "GR",
            "GT",
            "HN",
            "HK",
            "HU",
            "IS",
            "IE",
            "IT",
            "LV",
            "LT",
            "LU",
            "MY",
            "MT",
            "MX",
            "NL",
            "NZ",
            "NI",
            "NO",
            "PA",
            "PY",
            "PE",
            "PH",
            "PL",
            "PT",
            "SG",
            "SK",
            "ES",
            "SE",
            "CH",
            "TW",
            "TR",
            "UY",
            "US",
            "GB",
            "AD",
            "LI",
            "MC",
            "ID",
            "JP",
            "TH",
            "VN",
            "RO",
            "IL",
            "ZA",
            "SA",
            "AE",
            "BH",
            "QA",
            "OM",
            "KW",
            "EG",
            "MA",
            "DZ",
            "TN",
            "LB",
            "JO",
            "PS",
            "IN",
            "BY",
            "KZ",
            "MD",
            "UA",
            "AL",
            "BA",
            "HR",
            "ME",
            "MK",
            "RS",
            "SI",
            "KR",
            "BD",
            "PK",
            "LK",
            "GH",
            "KE",
            "NG",
            "TZ",
            "UG",
            "AG",
            "AM",
            "BS",
            "BB",
            "BZ",
            "BT",
            "BW",
            "BF",
            "CV",
            "CW",
            "DM",
            "FJ",
            "GM",
            "GE",
            "GD",
            "GW",
            "GY",
            "HT",
            "JM",
            "KI",
            "LS",
            "LR",
            "MW",
            "MV",
            "ML",
            "MH",
            "FM",
            "NA",
            "NR",
            "NE",
            "PW",
            "PG",
            "WS",
            "SM",
            "ST",
            "SN",
            "SC",
            "SL",
            "SB",
            "KN",
            "LC",
            "VC",
            "SR",
            "TL",
            "TO",
            "TT",
            "TV",
            "VU",
            "AZ",
            "BN",
            "BI",
            "KH",
            "CM",
            "TD",
            "KM",
            "GQ",
            "SZ",
            "GA",
            "GN",
            "KG",
            "LA",
            "MO",
            "MR",
            "MN",
            "NP",
            "RW",
            "TG",
            "UZ",
            "ZW",
            "BJ",
            "MG",
            "MU",
            "MZ",
            "AO",
            "CI",
            "DJ",
            "ZM",
            "CD",
            "CG",
            "IQ",
            "LY",
            "TJ",
            "VE",
            "ET",
            "XK"
          ],
          "external_urls": {
            "spotify": "https://open.spotify.com/album/6RBGm1BTZmgxk7kCiTHvNB"
          },
          "href": "https://api.spotify.com/v1/albums/6RBGm1BTZmgxk7kCiTHvNB",
          "id": "6RBGm1BTZmgxk7kCiTHvNB",
          "images": [
            {
              "height": 640,
              "url": "https://i.scdn.co/image/ab67616d0000b2739340c6cb93d104d5e2ada82a",
              "width": 640
            },
            {
              "height": 300,
              "url": "https://i.scdn.co/image/ab67616d00001e029340c6cb93d104d5e2ada82a",
              "width": 300
            },
            {
              "height": 64,
              "url": "https://i.scdn.co/image/ab67616d000048519340c6cb93d104d5e2ada82a",
              "width": 64
            }
          ],
          "name": "El Nuevo Leon",
          "release_date": "2020-12-16",
          "release_date_precision": "day",
          "total_tracks": 10,
          "type": "album",
          "uri": "spotify:album:6RBGm1BTZmgxk7kCiTHvNB"
        },
        "artists": [
          {
            "external_urls": {
              "spotify": "https://open.spotify.com/artist/4V2V4PaSblStayYVWTGDbZ"
            },
            "href": "https://api.spotify.com/v1/artists/4V2V4PaSblStayYVWTGDbZ",
            "id": "4V2V4PaSblStayYVWTGDbZ",
            "name": "Geassassin",
            "type": "artist",
            "uri": "spotify:artist:4V2V4PaSblStayYVWTGDbZ"
          },
          {
            "external_urls": {
              "spotify": "https://open.spotify.com/artist/7CvKsTEWv1BS3LydN8HgG6"
            },
            "href": "https://api.spotify.com/v1/artists/7CvKsTEWv1BS3LydN8HgG6",
            "id": "7CvKsTEWv1BS3LydN8HgG6",
            "name": "ILUMINATIK BUFFON",
            "type": "artist",
            "uri": "spotify:artist:7CvKsTEWv1BS3LydN8HgG6"
          }
        ],
        "available_markets": [
          "AR",
          "AU",
          "AT",
          "BE",
          "BO",
          "BR",
          "BG",
          "CA",
          "CL",
          "CO",
          "CR",
          "CY",
          "CZ",
          "DK",
          "DO",
          "DE",
          "EC",
          "EE",
          "SV",
          "FI",
          "FR",
          "GR",
          "GT",
          "HN",
          "HK",
          "HU",
          "IS",
          "IE",
          "IT",
          "LV",
          "LT",
          "LU",
          "MY",
          "MT",
          "MX",
          "NL",
          "NZ",
          "NI",
          "NO",
          "PA",
          "PY",
          "PE",
          "PH",
          "PL",
          "PT",
          "SG",
          "SK",
          "ES",
          "SE",
          "CH",
          "TW",
          "TR",
          "UY",
          "US",
          "GB",
          "AD",
          "LI",
          "MC",
          "ID",
          "JP",
          "TH",
          "VN",
          "RO",
          "IL",
          "ZA",
          "SA",
          "AE",
          "BH",
          "QA",
          "OM",
          "KW",
          "EG",
          "MA",
          "DZ",
          "TN",
          "LB",
          "JO",
          "PS",
          "IN",
          "BY",
          "KZ",
          "MD",
          "UA",
          "AL",
          "BA",
          "HR",
          "ME",
          "MK",
          "RS",
          "SI",
          "KR",
          "BD",
          "PK",
          "LK",
          "GH",
          "KE",
          "NG",
          "TZ",
          "UG",
          "AG",
          "AM",
          "BS",
          "BB",
          "BZ",
          "BT",
          "BW",
          "BF",
          "CV",
          "CW",
          "DM",
          "FJ",
          "GM",
          "GE",
          "GD",
          "GW",
          "GY",
          "HT",
          "JM",
          "KI",
          "LS",
          "LR",
          "MW",
          "MV",
          "ML",
          "MH",
          "FM",
          "NA",
          "NR",
          "NE",
          "PW",
          "PG",
          "WS",
          "SM",
          "ST",
          "SN",
          "SC",
          "SL",
          "SB",
          "KN",
          "LC",
          "VC",
          "SR",
          "TL",
          "TO",
          "TT",
          "TV",
          "VU",
          "AZ",
          "BN",
          "BI",
          "KH",
          "CM",
          "TD",
          "KM",
          "GQ",
          "SZ",
          "GA",
          "GN",
          "KG",
          "LA",
          "MO",
          "MR",
          "MN",
          "NP",
          "RW",
          "TG",
          "UZ",
          "ZW",
          "BJ",
          "MG",
          "MU",
          "MZ",
          "AO",
          "CI",
          "DJ",
          "ZM",
          "CD",
          "CG",
          "IQ",
          "LY",
          "TJ",
          "VE",
          "ET",
          "XK"
        ],
        "disc_number": 1,
        "duration_ms": 219506,
        "explicit": false,
        "external_ids": {
          "isrc": "DGA052013350"
        },
        "external_urls": {
          "spotify": "https://open.spotify.com/track/2A0K7UUKfqipqzJ4mgJN2n"
        },
        "href": "https://api.spotify.com/v1/tracks/2A0K7UUKfqipqzJ4mgJN2n",
        "id": "2A0K7UUKfqipqzJ4mgJN2n",
        "is_local": false,
        "name": "12 Am",
        "popularity": 28,
        "preview_url": "https://p.scdn.co/mp3-preview/391f0032dc0a8953293da57052eb436364a325a4?cid=5a0ffed4bc0642d794ffd4ab473c1b8f",
        "track_number": 4,
        "type": "track",
        "uri": "spotify:track:2A0K7UUKfqipqzJ4mgJN2n"
      },
      "played_at": "2023-10-09T21:54:07.498Z",
      "context": null
    }
  ]
}
